[
  {
    "name": "Advances In Natural Sciences-nanoscience And Nanotechnology",
    "publisher": "IOP Publishing and Vietnam Academy of Science and Technology",
    "info": [
      "https://www.ans.ac.vn/index.php/ansn"
    ],
    "forauthor": "https://www.ans.ac.vn/index.php/ansn/information/authors",
    "indexing": "Scopus, Inspec",
    "issn": "2043-6254",
    "mark": "25.0"
  },
  {
    "name": "Ieee Journal Of Quantum Electronics",
    "publisher": "IEEE Photonics Society",
    "info": [
      "https://ieeexplore.ieee.org/xpl/aboutJournal.jsp?punumber=3",
      "https://ieeexplore.ieee.org/xpl/tocresult.jsp?isnumber=6671407&punumber=3"
    ],
    "forauthor": "https://ieeexplore.ieee.org/xpl/aboutJournal.jsp?punumber=3",
    "indexing": "",
    "issn": "0018-9197",
    "mark": "30.0"
  },
  {
    "name": "Visual Neuroscience",
    "publisher": "Cambridge University Press",
    "info": [
      "https://www.ncbi.nlm.nih.gov/labs/journals/vis-neurosci/",
      "https://www.cambridge.org/core/journals/visual-neuroscience"
    ],
    "forauthor": "",
    "indexing": "Scopus",
    "issn": "0952-5238",
    "mark": "25.0"
  },
  {
    "name": "Asian Studies Review",
    "publisher": "Taylor & Francis",
    "info": [
      "https://www.tandfonline.com/loi/casr20",
      "https://www.tandfonline.com/action/journalInformation?journalCode=casr20"
    ],
    "forauthor": "https://www.tandfonline.com/action/authorSubmission?show=instructions&journalCode=casr20",
    "indexing": "SCOPUS",
    "issn": "1035-7823",
    "mark": "25.0"
  },
  {
    "name": "Ieee Transactions On Software Engineering",
    "publisher": "IEEE Computer Society",
    "info": [
      "https://ieeexplore.ieee.org/xpl/RecentIssue.jsp?punumber=32"
    ],
    "forauthor": "",
    "indexing": "indexing",
    "issn": "0098-5589",
    "mark": "45.0"
  },
  {
    "name": "Intelligent Data Analysis",
    "publisher": "Publisher",
    "info": [
      "https://www.iospress.nl/journal/intelligent-data-analysis/",
      "https://content.iospress.com/journals/intelligent-data-analysis/22/3"
    ],
    "forauthor": "https://www.iospress.nl/journal/intelligent-data-analysis/",
    "indexing": "Scopus, Inspec IET,Web of Science: Current Contents/Engineering, Computing and Technology",
    "issn": "1088-467X",
    "mark": "15.0"
  },
  {
    "name": "Advances In Applied Mathematics And Mechanics",
    "publisher": "Cambridge University Press",
    "info": [
      "https://www.scimagojr.com/journalsearch.php?q=21100201017&tip=sid",
      "https://www.cambridge.org/core/journals/advances-in-applied-mathematics-and-mechanics"
    ],
    "forauthor": "",
    "indexing": "indexing",
    "issn": "2070-0733",
    "mark": "25.0"
  },
  {
    "name": "Information Technology For Development",
    "publisher": "",
    "info": [
      "https://www.tandfonline.com/loi/titd20",
      "https://www.tandfonline.com/action/journalInformation?show=specialIssues&journalCode=titd20"
    ],
    "forauthor": "https://www.tandfonline.com/action/authorSubmission?show=instructions&journalCode=titd20",
    "indexing": "Scopus",
    "issn": "0268-1102",
    "mark": "25.0"
  },
  {
    "name": "Probability In The Engineering And Informational Sciences",
    "publisher": "Cambridge University Press",
    "info": [
      "https://www.cambridge.org/core/journals/probability-in-the-engineering-and-informational-sciences",
      "https://www.cambridge.org/core/journals/probability-in-the-engineering-and-informational-sciences/all-issues",
      "https://dl.acm.org/citation.cfm?id=1127596"
    ],
    "forauthor": "",
    "indexing": "indexing",
    "issn": "0269-9648",
    "mark": "20.0"
  },
  {
    "name": "Ieee Transactions On Evolutionary Computation",
    "publisher": "IEEE Computational Intelligence Society",
    "info": [
      "https://ieeexplore.ieee.org/xpl/aboutJournal.jsp?punumber=4235"
    ],
    "forauthor": "",
    "indexing": "indexing",
    "issn": "1089-778X",
    "mark": "50.0"
  },
  {
    "name": "Analysis And Applications",
    "publisher": "Publisher",
    "info": [
      "https://www.worldscientific.com/worldscinet/aa",
      "https://www.worldscientific.com/page/aa/aims-scope"
    ],
    "forauthor": "https://www.worldscientific.com/page/aa/submission-guidelines",
    "indexing": "Scopus",
    "issn": "0219-5305",
    "mark": "40.0"
  },
  {
    "name": "Quantum Information & Computation",
    "publisher": "Publisher",
    "info": [
      "http://www.rintonpress.com/journals/qic/",
      "https://dl.acm.org/citation.cfm?id=J1337"
    ],
    "forauthor": "http://www.rintonpress.com/journals/qic/qic-cover-3.pdf",
    "indexing": "INSPEC",
    "issn": "1533-7146",
    "mark": "30.0"
  },
  {
    "name": "Microsystem Technologies-micro-and Nanosystems- Information Storage And Processing Systems",
    "publisher": "Springer",
    "info": [
      "https://link.springer.com/journal/542",
      "https://link.springer.com/journal/volumesAndIssues/542",
      "https://www.springer.com/engineering/electronics/journal/542"
    ],
    "forauthor": "https://www.springer.com/engineering/electronics/journal/542",
    "indexing": "Scopus",
    "issn": "0946-7076",
    "mark": "15.0"
  },
  {
    "name": "Ieee Pervasive Computing",
    "publisher": "IEEE Computer Society",
    "info": [
      "https://ieeexplore.ieee.org/xpl/aboutJournal.jsp?punumber=7756"
    ],
    "forauthor": "",
    "indexing": "indexing",
    "issn": "1536-1268",
    "mark": "35.0"
  },
  {
    "name": "Asian Journal Of Technology Innovation",
    "publisher": "Taylor & Francis",
    "info": [
      "https://www.tandfonline.com/loi/rajt20",
      "https://www.researchgate.net/journal/1976-1597_Asian_Journal_of_Technology_Innovation"
    ],
    "forauthor": "https://www.tandfonline.com/action/authorSubmission?show=instructions&journalCode=rajt20",
    "indexing": "Scopus",
    "issn": "1976-1597",
    "mark": "20.0"
  },
  {
    "name": "Computer Science And Information Systems",
    "publisher": "ComSIS Consortium",
    "info": [
      "http://www.comsis.org/"
    ],
    "forauthor": "http://www.comsis.org/information.php",
    "indexing": "Scopus, IET bibliographic database Inspec",
    "issn": "1820-0214",
    "mark": "15.0"
  },
  {
    "name": "Journal Of Web Semantics",
    "publisher": "Publisher",
    "info": [
      "Info"
    ],
    "forauthor": "",
    "indexing": "indexing",
    "issn": "1570-8268",
    "mark": "40.0"
  },
  {
    "name": "Ieee Vehicular Technology Magazine",
    "publisher": "Elsevier",
    "info": [
      "https://www.journals.elsevier.com/journal-of-web-semantics/",
      "https://www.sciencedirect.com/journal/journal-of-web-semantics"
    ],
    "forauthor": "https://www.elsevier.com/journals/journal-of-web-semantics/1570-8268/guide-for-authors",
    "indexing": "Scopus",
    "issn": "1556-6072",
    "mark": "30.0"
  },
  {
    "name": "Information And Software Technology",
    "publisher": "Elsevier",
    "info": [
      "https://www.journals.elsevier.com/information-and-software-technology",
      "https://www.sciencedirect.com/journal/information-and-software-technology"
    ],
    "forauthor": "https://www.elsevier.com/journals/information-and-software-technology/0950-5849/guide-for-authors",
    "indexing": "Scopus, INSPEC Computer and Control Abstracts",
    "issn": "0950-5849",
    "mark": "35.0"
  },
  {
    "name": "Ieee Transactions On Neural Networks And Learning Systems",
    "publisher": "IEEE",
    "info": [
      "https://ieeexplore.ieee.org/xpl/aboutJournal.jsp?punumber=5962385"
    ],
    "forauthor": "https://mc.manuscriptcentral.com/societyimages/tnnls/tnnls-cover4-2235317-x.pdf",
    "indexing": "indexing",
    "issn": "2162-237X",
    "mark": "45.0"
  },
  {
    "name": "Applied Mathematics And Optimization",
    "publisher": "Springer",
    "info": [
      "https://link.springer.com/journal/245",
      "https://link.springer.com/journal/volumesAndIssues/245",
      "https://www.springer.com/mathematics/journal/245"
    ],
    "forauthor": "https://www.springer.com/mathematics/journal/245",
    "indexing": "Scopus",
    "issn": "0095-4616",
    "mark": "30.0"
  },
  {
    "name": "International Journal On Semantic Web And Information Systems",
    "publisher": "IGI Publishing Hershey",
    "info": [
      "https://dl.acm.org/citation.cfm?id=2687840",
      "https://www.igi-global.com/calls-for-papers/international-journal-semantic-web-information/1092"
    ],
    "forauthor": "",
    "indexing": "Scopus",
    "issn": "1552-6283",
    "mark": "40.0"
  },
  {
    "name": "Acm Transactions On Knowledge Discovery From Data",
    "publisher": "ACM New York",
    "info": [
      "https://tkdd.acm.org/",
      "https://dl.acm.org/citation.cfm?id=J1054"
    ],
    "forauthor": "https://tkdd.acm.org/authors.cfm",
    "indexing": "Scopus",
    "issn": "1556-4681",
    "mark": "40.0"
  },
  {
    "name": "Beilstein Journal Of Nanotechnology",
    "publisher": "Beilstein-Institut",
    "info": [
      "http://l2u.su/qGu",
      "https://www.beilstein-journals.org/bjnano/theJournal"
    ],
    "forauthor": "https://www.beilstein-journals.org/bjnano/authorInstructions",
    "indexing": "indexing",
    "issn": "2190-4286",
    "mark": "35.0"
  },
  {
    "name": "Acm Transactions On Reconfigurable Technology And Systems",
    "publisher": "ACM New York",
    "info": [
      "https://dl.acm.org/citation.cfm?id=J1151",
      "https://www.researchgate.net/journal/1936-7406_ACM_Transactions_on_Reconfigurable_Technology_and_Systems"
    ],
    "forauthor": "",
    "indexing": "indexing",
    "issn": "1936-7406",
    "mark": "20.0"
  },
  {
    "name": "Romanian Journal Of Information Science And Technology",
    "publisher": "Publisher",
    "info": [
      "http://www.romjist.ro/general-info.html"
    ],
    "forauthor": "http://www.romjist.ro/info-for-authors.html",
    "indexing": "indexing",
    "issn": "1453-8245",
    "mark": "15.0"
  },
  {
    "name": "Software And Systems Modeling",
    "publisher": "Springer",
    "info": [
      "https://link.springer.com/journal/10270",
      "https://link.springer.com/journal/volumesAndIssues/10270",
      "https://www.springer.com/computer/swe/journal/10270"
    ],
    "forauthor": "https://www.springer.com/computer/swe/journal/10270",
    "indexing": "Scopus, Computer Science Index",
    "issn": "1619-1366",
    "mark": "30.0"
  },
  {
    "name": "Computer Communication Review",
    "publisher": "ACM New York",
    "info": [
      "https://dl.acm.org/citation.cfm?id=J101",
      "https://dl.acm.org/citation.cfm?id=3213232&picked=prox"
    ],
    "forauthor": "http://www.sigcomm.org/for-authors/ccr-author-information",
    "indexing": "Scopus",
    "issn": "0146-4833",
    "mark": "35.0"
  },
  {
    "name": "Advances In Applied Probability",
    "publisher": "Applied Probability Trus",
    "info": [
      "https://www.cambridge.org/core/journals/advances-in-applied-probability",
      "http://www.appliedprobability.org/content.aspx?Group=journals&Page=apjournals"
    ],
    "forauthor": "",
    "indexing": "indexing",
    "issn": "0001-8678",
    "mark": "25.0"
  },
  {
    "name": "Ieee Transactions On Knowledge And Data Engineering",
    "publisher": "IEEE Computer Society",
    "info": [
      "https://ieeexplore.ieee.org/xpl/aboutJournal.jsp?punumber=69",
      "https://dl.acm.org/citation.cfm?id=627291"
    ],
    "forauthor": "",
    "indexing": "indexing",
    "issn": "1041-4347",
    "mark": "40.0"
  },
  {
    "name": "Advances In Complex Systems",
    "publisher": "World Scientific (Singapore)",
    "info": [
      "https://www.worldscientific.com/worldscinet/acs"
    ],
    "forauthor": "https://www.worldscientific.com/page/acs/submission-guidelines https://www.worldscientific.com/loi/acs",
    "indexing": "Scopus, Web of Science",
    "issn": "0219-5259",
    "mark": "25.0"
  },
  {
    "name": "Ieee Transactions On Parallel And Distributed Systems",
    "publisher": "IEEE Press Piscataway",
    "info": [
      "https://ieeexplore.ieee.org/xpl/aboutJournal.jsp?punumber=71",
      "https://dl.acm.org/citation.cfm?id=2360765&picked=prox"
    ],
    "forauthor": "",
    "indexing": "indexing",
    "issn": "1045-9219",
    "mark": "40.0"
  },
  {
    "name": "International Journal Of Web Services Research",
    "publisher": "Quarterly",
    "info": [
      "https://www.igi-global.com/journal/international-journal-web-services-research/1079"
    ],
    "forauthor": "https://www.igi-global.com/publish/resources/journal-guidelines-for-submission.pdf",
    "indexing": "Web of Science Science Citation Index Expanded (SCIE), SCOPUS, Inspec",
    "issn": "1545-7362",
    "mark": "15.0"
  },
  {
    "name": "Ieee Transactions On Dependable And Secure Computing",
    "publisher": "IEEE Computer Society Press Los Alamitos",
    "info": [
      "https://ieeexplore.ieee.org/xpl/aboutJournal.jsp?punumber=8858",
      "https://dl.acm.org/citation.cfm?id=1512150&picked=prox"
    ],
    "forauthor": "",
    "indexing": "Scopus",
    "issn": "1545-5971",
    "mark": "35.0"
  },
  {
    "name": "Ieee Signal Processing Magazine",
    "publisher": "Institute of Electrical & Electronics Engineers",
    "info": [
      "https://ieeexplore.ieee.org/xpl/aboutJournal.jsp?punumber=79",
      "https://www.researchgate.net/journal/1053-5888_IEEE_Signal_Processing_Magazine"
    ],
    "forauthor": "",
    "indexing": "indexing",
    "issn": "1053-5888",
    "mark": "50.0"
  },
  {
    "name": "Journal Of Zhejiang University-science C-computers & Electronics",
    "publisher": "ZHEJIANG UNIV,Zhejiang University Press",
    "info": [
      "http://www.jzus.zju.edu.cn/archives_c.php",
      "http://www.jzus.zju.edu.cn/archives_c.php"
    ],
    "forauthor": "",
    "indexing": "indexing",
    "issn": "1869-1951",
    "mark": "15.0"
  },
  {
    "name": "Ieee Transactions On Device And Materials Reliability",
    "publisher": "IEEE Electron Devices Society,IEEE Reliability Society",
    "info": [
      "https://ieeexplore.ieee.org/stamp/stamp.jsp?arnumber=8024084",
      "https://ieeexplore.ieee.org/xpl/aboutJournal.jsp?punumber=7298"
    ],
    "forauthor": "",
    "indexing": "indexing",
    "issn": "1530-4388",
    "mark": "30.0"
  },
  {
    "name": "Ai Communications",
    "publisher": "Institute of Science",
    "info": [
      "https://www.iospress.nl/journal/ai-communications/",
      "https://www.abe.pl/en/journal/11268/ai-communications"
    ],
    "forauthor": "https://www.iospress.nl/journal/ai-communications/",
    "indexing": "Scopus, Inspec IET, Web of Science: Journal Citation Reports/Science Edition,",
    "issn": "0921-7126",
    "mark": "15.0"
  },
  {
    "name": "Combinatorics Probability & Computing",
    "publisher": "Cambridge",
    "info": [
      "https://www.cambridge.org/core/journals/combinatorics-probability-and-computing",
      "https://www.cambridge.org/core/journals/combinatorics-probability-and-computing/all-issues"
    ],
    "forauthor": "https://www.cambridge.org/core/services/authors",
    "indexing": "Scopus",
    "issn": "0963-5483",
    "mark": "25.0"
  },
  {
    "name": "Journal Of Computer And System Sciences",
    "publisher": "Elsevier",
    "info": [
      "https://www.journals.elsevier.com/journal-of-computer-and-system-sciences",
      "https://www.sciencedirect.com/journal/journal-of-computer-and-system-sciences"
    ],
    "forauthor": "https://www.elsevier.com/journals/journal-of-computer-and-system-sciences/0022-0000/guide-for-authors",
    "indexing": "Scopus",
    "issn": "0022-0000",
    "mark": "30.0"
  },
  {
    "name": "Applied Computational Electromagnetics Society Journal",
    "publisher": "Applied Computational Electromagnetics Society",
    "info": [
      "https://www.researchgate.net/journal/1054-4887_Applied_Computational_Electromagnetics_Society_Journal",
      "https://www.scimagojr.com/journalsearch.php?q=13200&tip=sid"
    ],
    "forauthor": "",
    "indexing": "indexing",
    "issn": "1054-4887",
    "mark": "25.0"
  },
  {
    "name": "Advanced Engineering Informatics",
    "publisher": "Elsevier",
    "info": [
      "https://www.journals.elsevier.com/advanced-engineering-informatics"
    ],
    "forauthor": "https://www.elsevier.com/journals/advanced-engineering-informatics/1474-0346/guide-for-authors",
    "indexing": "Scopus",
    "issn": "1474-0346",
    "mark": "40.0"
  },
  {
    "name": "Science China-information Sciences",
    "publisher": "Springer",
    "info": [
      "https://www.springer.com/computer/information+systems+and+applications/journal/11432",
      "https://link.springer.com/journal/11432",
      "https://link.springer.com/journal/volumesAndIssues/11432"
    ],
    "forauthor": "https://www.springer.com/computer/information+systems+and+applications/journal/11432",
    "indexing": "SCOPUS",
    "issn": "1674-733X",
    "mark": "20.0"
  },
  {
    "name": "Ieee Electrical Insulation Magazine",
    "publisher": "IEEE Electrical Insulation Society",
    "info": [
      "https://ieeexplore.ieee.org/xpl/aboutJournal.jsp?punumber=57",
      "https://www.researchgate.net/journal/0883-7554_IEEE_Electrical_Insulation_Magazine"
    ],
    "forauthor": "",
    "indexing": "Scopus",
    "issn": "0883-7554",
    "mark": "30.0"
  },
  {
    "name": "Iet Software",
    "publisher": "Institution of Engineering and Technology (IET) (United Kingdom)",
    "info": [
      "http://digital-library.theiet.org/content/journals/iet-sen",
      "http://digital-library.theiet.org/content/journals/iet-sen/12/3"
    ],
    "forauthor": "",
    "indexing": "Scopus",
    "issn": "1751-8806",
    "mark": "15.0"
  },
  {
    "name": "African Journal Of Library Archives And Information Science",
    "publisher": "Archlib & Information Services Ltd.",
    "info": [
      "https://www.researchgate.net/journal/0795-4778_African_Journal_of_Library_Archives_and_Information_Science",
      "https://www.abe.pl/en/journal/0795-4778/"
    ],
    "forauthor": "",
    "indexing": "indexing",
    "issn": "0795-4778",
    "mark": "15.0"
  },
  {
    "name": "Asian Journal Of Communication",
    "publisher": "Taylor & Francis",
    "info": [
      "https://www.tandfonline.com/loi/rajc20",
      "https://www.tandfonline.com/action/journalInformation?show=aimsScope&journalCode=rajc20"
    ],
    "forauthor": "https://www.tandfonline.com/action/authorSubmission?show=instructions&journalCode=rajc20",
    "indexing": "indexing",
    "issn": "0129-2986",
    "mark": "20.0"
  },
  {
    "name": "Acm Transactions On Software Engineering And Methodology",
    "publisher": "ACM New York",
    "info": [
      "https://dl.acm.org/citation.cfm?id=J790",
      "https://dl.acm.org/citation.cfm?id=3208361&picked=prox",
      "https://www.researchgate.net/journal/1049-331X_ACM_Transactions_on_Software_Engineering_and_Methodology"
    ],
    "forauthor": "",
    "indexing": "indexing",
    "issn": "1049-331X",
    "mark": "35.0"
  },
  {
    "name": "Mobile Information Systems",
    "publisher": "IOS Press",
    "info": [
      "https://www.iospress.nl/journal/mobile-information-systems/",
      "https://www.iospress.nl/journal/mobile-information-systems/1574-017X"
    ],
    "forauthor": "",
    "indexing": "indexing",
    "issn": "1574-017X",
    "mark": "25.0"
  },
  {
    "name": "Computer Vision And Image Understanding",
    "publisher": "Elsevier",
    "info": [
      "https://www.journals.elsevier.com/computer-vision-and-image-understanding/"
    ],
    "forauthor": "https://www.elsevier.com/journals/computer-vision-and-image-understanding/1077-3142/guide-for-authors",
    "indexing": "Scopus, Index to Scientific Reviews",
    "issn": "1077-3142",
    "mark": "35.0"
  },
  {
    "name": "Acm Sigplan Notices",
    "publisher": "ACM New York",
    "info": [
      "https://dl.acm.org/citation.cfm?id=J706",
      "https://dl.acm.org/citation.cfm?id=3200691&picked=prox"
    ],
    "forauthor": "",
    "indexing": "Scopus",
    "issn": "0362-1340",
    "mark": "20.0"
  },
  {
    "name": "Journal Of Universal Computer Science",
    "publisher": "[Graz] : [J.UCS Consortium]",
    "info": [
      "http://www.jucs.org/jucs_info/aims"
    ],
    "forauthor": "",
    "indexing": "Web of Science (Thomson Reuters), Scopus",
    "issn": "0948-695X",
    "mark": "20.0"
  },
  {
    "name": "Journal Of Educational Computing Research",
    "publisher": "Baywood",
    "info": [
      "http://journals.sagepub.com/home/jec",
      "https://uk.sagepub.com/en-gb/eur/journal/journal-educational-computing-research"
    ],
    "forauthor": "https://uk.sagepub.com/en-gb/eur/journal/journal-educational-computing-research#submission-guidelines",
    "indexing": "SCOPUS",
    "issn": "0735-6331",
    "mark": "25.0"
  },
  {
    "name": "Acm Transactions On Design Automation Of Electronic Systems",
    "publisher": "ACM New York",
    "info": [
      "https://dl.acm.org/citation.cfm?id=J776",
      "https://dl.acm.org/citation.cfm?id=3217208&picked=prox"
    ],
    "forauthor": "",
    "indexing": "Scopus",
    "issn": "1084-4309",
    "mark": "20.0"
  },
  {
    "name": "Ieice Transactions On Electronics",
    "publisher": "The Institute of Electronics, Information and Communication Engineers",
    "info": [
      "https://www.jstage.jst.go.jp/browse/transele",
      "http://www.oxfordjournals.org/our_journals/ietele/about.html"
    ],
    "forauthor": "https://www.jstage.jst.go.jp/static/pages/ForAuthors/-char/en",
    "indexing": "indexing",
    "issn": "0916-8524",
    "mark": "15.0"
  },
  {
    "name": "Computer Speech And Language",
    "publisher": "Elsevier",
    "info": [
      "https://www.journals.elsevier.com/computer-speech-and-language"
    ],
    "forauthor": "https://www.elsevier.com/journals/computer-speech-and-language/0885-2308/guide-for-authors",
    "indexing": "Scopus, INSPEC",
    "issn": "0885-2308",
    "mark": "25.0"
  },
  {
    "name": "Ieee Transactions On Services Computing",
    "publisher": "IEEE Computer Society Washington",
    "info": [
      "https://dl.acm.org/citation.cfm?id=1638592",
      "https://ieeexplore.ieee.org/xpl/aboutJournal.jsp?punumber=4629386"
    ],
    "forauthor": "",
    "indexing": "Scopus",
    "issn": "1939-1374",
    "mark": "45.0"
  },
  {
    "name": "Ieee Design & Test",
    "publisher": "IEEE Circuits and Systems Society",
    "info": [
      "https://ieeexplore.ieee.org/xpl/aboutJournal.jsp?punumber=6221038"
    ],
    "forauthor": "",
    "indexing": "Scopus",
    "issn": "2168-2356",
    "mark": "30.0"
  },
  {
    "name": "Ieee Transactions On Wireless Communications",
    "publisher": "IEEE Communications Society, IEEE Signal Processing Society",
    "info": [
      "https://ieeexplore.ieee.org/xpl/aboutJournal.jsp?punumber=7693"
    ],
    "forauthor": "",
    "indexing": "Inspec",
    "issn": "1536-1276",
    "mark": "45.0"
  },
  {
    "name": "Ieee Journal Of Solid-state Circuits",
    "publisher": "IEEE Solid-State Circuits Society",
    "info": [
      "https://ieeexplore.ieee.org/xpl/aboutJournal.jsp?punumber=4"
    ],
    "forauthor": "",
    "indexing": "Scopus",
    "issn": "0018-9200",
    "mark": "40.0"
  },
  {
    "name": "Applied Nursing Research",
    "publisher": "Elsevier",
    "info": [
      "https://www.journals.elsevier.com/applied-nursing-research"
    ],
    "forauthor": "https://www.elsevier.com/journals/applied-nursing-research/0897-1897/guide-for-authors",
    "indexing": "Scopus",
    "issn": "0897-1897",
    "mark": "30.0"
  },
  {
    "name": "Ieee Transactions On Industrial Informatics",
    "publisher": "IEEE Industrial Electronics Society, IEEE Computer Society, IEEE Industrial Applications Society, IEEE Robotics and Automation Society, IEEE Systems, Man, and Cybernetics Society",
    "info": [
      "https://ieeexplore.ieee.org/xpl/aboutJournal.jsp?punumber=9424"
    ],
    "forauthor": "",
    "indexing": "Scopus",
    "issn": "1551-3203",
    "mark": "50.0"
  },
  {
    "name": "Neural Computation",
    "publisher": "The Mit Press",
    "info": [
      "https://www.mitpressjournals.org/loi/neco"
    ],
    "forauthor": "https://www.mitpressjournals.org/journals/neco/sub",
    "indexing": "Scopus",
    "issn": "0899-7667",
    "mark": "30.0"
  },
  {
    "name": "Advanced Engineering Materials",
    "publisher": "Publisher",
    "info": [
      "http://www.wiley-vch.de/de/shop/journals/121-advanced-engineering-materials-2266-de",
      "https://www.researchgate.net/journal/1527-2648_Advanced_Engineering_Materials"
    ],
    "forauthor": "",
    "indexing": "Scopus",
    "issn": "1438-1656",
    "mark": "30.0"
  },
  {
    "name": "Mathematical Structures In Computer Science",
    "publisher": "Cambridge University Press New York",
    "info": [
      "https://www.cambridge.org/core/journals/mathematical-structures-in-computer-science",
      "https://www.cambridge.org/core/journals/mathematical-structures-in-computer-science/information"
    ],
    "forauthor": "https://mc.manuscriptcentral.com/mscs",
    "indexing": "Web of Science, Inspec, Scopus",
    "issn": "0960-1295",
    "mark": "20.0"
  },
  {
    "name": "Acm Transactions On Computer-human Interaction",
    "publisher": "ACM New York",
    "info": [
      "https://dl.acm.org/citation.cfm?id=J756"
    ],
    "forauthor": "",
    "indexing": "Scopus",
    "issn": "1073-0516",
    "mark": "30.0"
  },
  {
    "name": "Advances In Applied Mathematics",
    "publisher": "Elsevier",
    "info": [
      "https://www.journals.elsevier.com/advances-in-applied-mathematics/"
    ],
    "forauthor": "https://www.elsevier.com/journals/advances-in-applied-mathematics/0196-8858/guide-for-authors",
    "indexing": "Scopus",
    "issn": "0196-8858",
    "mark": "30.0"
  },
  {
    "name": "Ieee Transactions On Automatic Control",
    "publisher": "IEEE Control Systems Society",
    "info": [
      "https://ieeexplore.ieee.org/xpl/aboutJournal.jsp?punumber=9"
    ],
    "forauthor": "",
    "indexing": "Scopus",
    "issn": "0018-9286",
    "mark": "40.0"
  },
  {
    "name": "Advances In Structural Engineering",
    "publisher": "Publisher",
    "info": [
      "http://journals.sagepub.com/loi/ase",
      "https://uk.sagepub.com/en-gb/eur/advances-in-structural-engineering/journal202466#description"
    ],
    "forauthor": "",
    "indexing": "Scopus",
    "issn": "1369-4332",
    "mark": "20.0"
  },
  {
    "name": "Journal Of Management Information Systems",
    "publisher": "M. E. Sharpe, Inc. Armonk, NY, USA",
    "info": [
      "https://dl.acm.org/citation.cfm?id=81918",
      "http://miar.ub.edu/issn/0742-1222"
    ],
    "forauthor": "https://dl.acm.org/citation.cfm?id=81918",
    "indexing": "Scopus, INSPEC",
    "issn": "0742-1222",
    "mark": "40.0"
  },
  {
    "name": "Ieee Design & Test Of Computers",
    "publisher": "IEEE Council on Electronic Design and Automation",
    "info": [
      "https://ieeexplore.ieee.org/xpl/aboutJournal.jsp?punumber=54"
    ],
    "forauthor": "",
    "indexing": "indexing",
    "issn": "0740-7475",
    "mark": "30.0"
  },
  {
    "name": "Informs Journal On Computing",
    "publisher": "Publisher",
    "info": [
      "https://pubsonline.informs.org/journal/ijoc",
      "https://www.informs.org/Publications/INFORMS-Journals/INFORMS-Journal-on-Computing"
    ],
    "forauthor": "",
    "indexing": "Scopus",
    "issn": "1091-9856",
    "mark": "35.0"
  },
  {
    "name": "Journal Of Computer Information Systems",
    "publisher": "Taylor & Francis",
    "info": [
      "https://www.tandfonline.com/loi/ucis20",
      "https://www.tandfonline.com/action/journalInformation?journalCode=ucis20"
    ],
    "forauthor": "https://www.tandfonline.com/action/authorSubmission?show=instructions&journalCode=ucis20",
    "indexing": "Scopus, Inspec",
    "issn": "0887-4417",
    "mark": "20.0"
  },
  {
    "name": "Future Generation Computer Systems-the International Journal Of Grid Computing And Escience",
    "publisher": "Elsevier",
    "info": [
      "https://www.journals.elsevier.com/future-generation-computer-systems"
    ],
    "forauthor": "https://www.elsevier.com/journals/future-generation-computer-systems/0167-739x/guide-for-authors",
    "indexing": "Scopus, INSPEC Information Services",
    "issn": "0167-739X",
    "mark": "40.0"
  },
  {
    "name": "International Journal Of Pattern Recognition And Artificial Intelligence",
    "publisher": "Publisher",
    "info": [
      "https://www.worldscientific.com/toc/ijprai/0/ja",
      "https://www.researchgate.net/journal/0218-0014_International_Journal_of_Pattern_Recognition_and_Artificial_Intelligence"
    ],
    "forauthor": "",
    "indexing": "Scopus",
    "issn": "0218-0014",
    "mark": "20.0"
  },
  {
    "name": "Journal Of Functional Programming",
    "publisher": "Cambridge University Press New York",
    "info": [
      "https://www.cambridge.org/core/journals/journal-of-functional-programming",
      "https://www.cambridge.org/core/journals/journal-of-functional-programming/information"
    ],
    "forauthor": "",
    "indexing": "Scopus",
    "issn": "0956-7968",
    "mark": "20.0"
  },
  {
    "name": "Ieee Transactions On Consumer Electronics",
    "publisher": "IEEE Consumer Electronics Society",
    "info": [
      "https://ieeexplore.ieee.org/xpl/aboutJournal.jsp?punumber=30",
      "https://dl.acm.org/citation.cfm?id=2275734"
    ],
    "forauthor": "",
    "indexing": "Scopus",
    "issn": "0098-3063",
    "mark": "25.0"
  },
  {
    "name": "Ieee Transactions On Visualization And Computer Graphics",
    "publisher": "IEEE Computer Society",
    "info": [
      "https://ieeexplore.ieee.org/xpl/aboutJournal.jsp?punumber=2945"
    ],
    "forauthor": "",
    "indexing": "Scopus",
    "issn": "1077-2626",
    "mark": "40.0"
  },
  {
    "name": "Acm Transactions On Computational Logic",
    "publisher": "ACM New York",
    "info": [
      "https://dl.acm.org/citation.cfm?id=J773"
    ],
    "forauthor": "",
    "indexing": "Scopus",
    "issn": "1529-3785",
    "mark": "40.0"
  },
  {
    "name": "Acm Transactions On Computing Education",
    "publisher": "ACM New York",
    "info": [
      "https://dl.acm.org/citation.cfm?id=J1193"
    ],
    "forauthor": "",
    "indexing": "Scopus",
    "issn": "1946-6226",
    "mark": "15.0"
  },
  {
    "name": "Neural Networks",
    "publisher": "Elsevier",
    "info": [
      "https://www.sciencedirect.com/journal/neural-networks"
    ],
    "forauthor": "https://www.elsevier.com/journals/neural-networks/0893-6080/guide-for-authors",
    "indexing": "Scopus",
    "issn": "0893-6080",
    "mark": "30.0"
  },
  {
    "name": "International Journal Of High Performance Computing Applications",
    "publisher": "Publisher",
    "info": [
      "http://journals.sagepub.com/loi/hpc",
      "http://journals.sagepub.com/home/hpc"
    ],
    "forauthor": "",
    "indexing": "Scopus",
    "issn": "1094-3420",
    "mark": "30.0"
  },
  {
    "name": "Mathematics And Computers In Simulation",
    "publisher": "Elsevier",
    "info": [
      "https://www.journals.elsevier.com/mathematics-and-computers-in-simulation"
    ],
    "forauthor": "https://www.elsevier.com/journals/mathematics-and-computers-in-simulation/0378-4754/guide-for-authors",
    "indexing": "Scopus, Web of Science, INSPEC Information Services, Web of Science",
    "issn": "0378-4754",
    "mark": "25.0"
  },
  {
    "name": "Circuit World",
    "publisher": "Emerald Group",
    "info": [
      "https://www.emeraldinsight.com/loi/cw",
      "http://www.emeraldgrouppublishing.com/products/journals/journals.htm?id=cw"
    ],
    "forauthor": "",
    "indexing": "Scopus, INSPEC",
    "issn": "0305-6120",
    "mark": "20.0"
  },
  {
    "name": "Advances In Nursing Science",
    "publisher": "Lippincott Williams & Wilkins (LWW) Impact Factor",
    "info": [
      "https://journals.lww.com/advancesinnursingscience/pages/default.aspx"
    ],
    "forauthor": "https://journals.lww.com/advancesinnursingscience/Pages/Instructions-for-Authors.aspx https://shop.lww.com/Advances-in-Nursing-Science/p/0161-9268",
    "indexing": "Scopus",
    "issn": "0161-9268",
    "mark": "25.0"
  },
  {
    "name": "Turkish Journal Of Electrical Engineering And Computer Sciences",
    "publisher": "Publisher",
    "info": [
      "https://journals.tubitak.gov.tr/elektrik/index.htm;jsessionid=6034C0725F59B62EA4EA6657C911CAD9",
      "https://journals.tubitak.gov.tr/elektrik/lastIssue.htm"
    ],
    "forauthor": "https://journals.tubitak.gov.tr/elektrik/instructionsForAuthors.htm",
    "indexing": "Scopus",
    "issn": "1300-0632",
    "mark": "20.0"
  },
  {
    "name": "Journal Of Web Engineering",
    "publisher": "Rinton Press",
    "info": [
      "http://www.rintonpress.com/journals/jwe/"
    ],
    "forauthor": "http://www.rintonpress.com/journals/jwe/JWE-cover-3.pdf",
    "indexing": "Scopus",
    "issn": "1540-9589",
    "mark": "15.0"
  },
  {
    "name": "Science Of Computer Programming",
    "publisher": "Elsavier",
    "info": [
      "https://www.journals.elsevier.com/science-of-computer-programming"
    ],
    "forauthor": "https://www.elsevier.com/journals/science-of-computer-programming/0167-6423/guide-for-authors",
    "indexing": "Scopus",
    "issn": "0167-6423",
    "mark": "20.0"
  },
  {
    "name": "Ieee Journal On Emerging And Selected Topics In Circuits And Systems",
    "publisher": "IEEE Circuits and Systems Society",
    "info": [
      "https://ieeexplore.ieee.org/document/7429973/",
      "https://ieeexplore.ieee.org/xpl/aboutJournal.jsp?punumber=5503868"
    ],
    "forauthor": "",
    "indexing": "Scopus",
    "issn": "2156-3357",
    "mark": "30.0"
  },
  {
    "name": "Ieee Transactions On Image Processing",
    "publisher": "IEEE Signal Processing Society",
    "info": [
      "https://ieeexplore.ieee.org/xpl/aboutJournal.jsp?punumber=83"
    ],
    "forauthor": "",
    "indexing": "Scopus",
    "issn": "1057-7149",
    "mark": "45.0"
  },
  {
    "name": "Computer Networks",
    "publisher": "Elsevier",
    "info": [
      "https://www.journals.elsevier.com/computer-networks"
    ],
    "forauthor": "https://www.elsevier.com/journals/computer-networks/1389-1286/guide-for-authors",
    "indexing": "Scopus, Inspec",
    "issn": "1389-1286",
    "mark": "35.0"
  },
  {
    "name": "Computer Assisted Language Learning",
    "publisher": "Taylor & Francis",
    "info": [
      "https://www.tandfonline.com/loi/ncal20"
    ],
    "forauthor": "https://www.tandfonline.com/action/authorSubmission?show=instructions&journalCode=ncal20",
    "indexing": "Scopus",
    "issn": "0958-8221",
    "mark": "35.0"
  },
  {
    "name": "Computers & Electrical Engineering",
    "publisher": "Elsevier",
    "info": [
      "https://www.journals.elsevier.com/computers-and-electrical-engineering"
    ],
    "forauthor": "https://www.elsevier.com/journals/computers-and-electrical-engineering/0045-7906/guide-for-authors",
    "indexing": "INSPEC, Scopus",
    "issn": "0045-7906",
    "mark": "20.0"
  },
  {
    "name": "Ieee Transactions On Automation Science And Engineering",
    "publisher": "IEEE Robotics and Automation Society",
    "info": [
      "https://ieeexplore.ieee.org/xpl/aboutJournal.jsp?punumber=8856"
    ],
    "forauthor": "",
    "indexing": "Scopus",
    "issn": "1545-5955",
    "mark": "35.0"
  },
  {
    "name": "Ieee Transactions On Computers",
    "publisher": "IEEE Computer Society",
    "info": [
      "https://ieeexplore.ieee.org/xpl/aboutJournal.jsp?punumber=12"
    ],
    "forauthor": "",
    "indexing": "Scopus",
    "issn": "0018-9340",
    "mark": "35.0"
  },
  {
    "name": "Ieee Spectrum",
    "publisher": "IEEE",
    "info": [
      "https://ieeexplore.ieee.org/xpl/aboutJournal.jsp?punumber=6"
    ],
    "forauthor": "",
    "indexing": "Scopus",
    "issn": "0018-9235",
    "mark": "25.0"
  },
  {
    "name": "Computer Supported Cooperative Work-the Journal Of Collaborative Computing",
    "publisher": "Springer",
    "info": [
      "https://www.springer.com/computer/journal/10606",
      "https://link.springer.com/journal/volumesAndIssues/10606",
      "https://www.springer.com/gp/book/9783540669845"
    ],
    "forauthor": "https://www.springer.com/gp/book/9783540669845",
    "indexing": "SCOPUS",
    "issn": "0925-9724",
    "mark": "25.0"
  },
  {
    "name": "Enterprise Information Systems",
    "publisher": "Taylor & Francis",
    "info": [
      "https://www.tandfonline.com/loi/teis20",
      "https://www.tandfonline.com/action/journalInformation?show=aimsScope&journalCode=teis20",
      "https://www.tandfonline.com/action/journalInformation?journalCode=teis20"
    ],
    "forauthor": "https://www.tandfonline.com/action/authorSubmission?show=instructions&journalCode=teis20",
    "indexing": "Scopus",
    "issn": "1751-7575",
    "mark": "50.0"
  },
  {
    "name": "Ai Edam-artificial Intelligence For Engineering Design Analysis And Manufacturing",
    "publisher": "Cambridge",
    "info": [
      "https://www.cambridge.org/core/journals/ai-edam",
      "https://www.cambridge.org/core/journals/ai-edam/information"
    ],
    "forauthor": "https://mc.manuscriptcentral.com/aie",
    "indexing": "Scopus",
    "issn": "0890-0604",
    "mark": ""
  },
  {
    "name": "Ieee Transactions On Pattern Analysis And Machine Intelligence",
    "publisher": "IEEE Computer Society",
    "info": [
      "https://ieeexplore.ieee.org/xpl/aboutJournal.jsp?punumber=34"
    ],
    "forauthor": "",
    "indexing": "Scopus",
    "issn": "0162-8828",
    "mark": "50.0"
  },
  {
    "name": "Mathematical And Computer Modelling Of Dynamical Systems",
    "publisher": "Taylor & Francis",
    "info": [
      "https://www.tandfonline.com/loi/nmcm20",
      "https://www.tandfonline.com/action/journalInformation?show=aimsScope&journalCode=nmcm20"
    ],
    "forauthor": "https://www.tandfonline.com/action/authorSubmission?show=instructions&journalCode=nmcm20",
    "indexing": "Scopus, Inspec",
    "issn": "1387-3954",
    "mark": "20.0"
  },
  {
    "name": "Acm Transactions On Graphics",
    "publisher": "ACM New York",
    "info": [
      "https://dl.acm.org/citation.cfm?id=J778",
      "https://en.wikipedia.org/wiki/ACM_Transactions_on_Graphics"
    ],
    "forauthor": "",
    "indexing": "Scopus",
    "issn": "0730-0301",
    "mark": "50.0"
  },
  {
    "name": "Ieee Robotics & Automation Magazine",
    "publisher": "IEEE Robotics and Automation Society",
    "info": [
      "https://ieeexplore.ieee.org/xpl/aboutJournal.jsp?punumber=100"
    ],
    "forauthor": "",
    "indexing": "Scopus",
    "issn": "1070-9932",
    "mark": "40.0"
  },
  {
    "name": "Program-electronic Library And Information Systems",
    "publisher": "Data Technologies and Applications",
    "info": [
      "https://www.emeraldinsight.com/loi/prog",
      "https://www.learntechlib.org/j/ISSN-0033-0337/"
    ],
    "forauthor": "",
    "indexing": "Scopus",
    "issn": "0033-0337",
    "mark": "20.0"
  },
  {
    "name": "Ieee Wireless Communications",
    "publisher": "IEEE Communications Society",
    "info": [
      "https://ieeexplore.ieee.org/xpl/aboutJournal.jsp?punumber=7742"
    ],
    "forauthor": "",
    "indexing": "Inspec",
    "issn": "1536-1284",
    "mark": "50.0"
  },
  {
    "name": "Intelligent Automation And Soft Computing",
    "publisher": "TSI Press",
    "info": [
      "https://www.researchgate.net/journal/1079-8587_Intelligent_Automation_and_Soft_Computing",
      "https://www.tandfonline.com/toc/tasj20/current",
      "https://www.tandfonline.com/action/journalInformation?journalCode=tasj20",
      "https://www.tandfonline.com/action/journalInformation?show=aimsScope&journalCode=tasj20"
    ],
    "forauthor": "",
    "indexing": "Inspec",
    "issn": "1079-8587",
    "mark": "15.0"
  },
  {
    "name": "Journal Of Parallel And Distributed Computing",
    "publisher": "Elsevier",
    "info": [
      "https://www.journals.elsevier.com/journal-of-parallel-and-distributed-computing"
    ],
    "forauthor": "https://www.elsevier.com/journals/journal-of-parallel-and-distributed-computing/0743-7315/guide-for-authors",
    "indexing": "Scopus",
    "issn": "0743-7315",
    "mark": "30.0"
  },
  {
    "name": "Computing And Informatics",
    "publisher": "DOI (Digital Object Identifier).",
    "info": [
      "http://www.cai.sk/ojs/index.php/cai"
    ],
    "forauthor": "",
    "indexing": "INSPEC, SCOPUS",
    "issn": "1335-9150",
    "mark": "15.0"
  },
  {
    "name": "International Journal Of Cooperative Information Systems",
    "publisher": "Publisher",
    "info": [
      "https://www.worldscientific.com/worldscinet/ijcis",
      "https://www.worldscientific.com/page/ijcis/aims-scope"
    ],
    "forauthor": "",
    "indexing": "Scopus",
    "issn": "0218-8430",
    "mark": "20.0"
  },
  {
    "name": "Information And Computation",
    "publisher": "Elsevier",
    "info": [
      "https://www.journals.elsevier.com/information-and-computation"
    ],
    "forauthor": "https://www.elsevier.com/journals/information-and-computation/0890-5401/guide-for-authors",
    "indexing": "Scopus",
    "issn": "0890-5401",
    "mark": "25.0"
  },
  {
    "name": "Ieice Transactions On Information And Systems",
    "publisher": "The Institute of Electronics, Information and Communication Engineers",
    "info": [
      "https://dl.acm.org/citation.cfm?id=J988",
      "https://www.jstage.jst.go.jp/browse/transinf",
      "https://www.jstage.jst.go.jp/browse/transinf/_pubinfo/-char/en"
    ],
    "forauthor": "https://www.jstage.jst.go.jp/static/pages/ForAuthors/-char/en",
    "indexing": "indexing",
    "issn": "0916-8532",
    "mark": "15.0"
  },
  {
    "name": "Advances In Engineering Software",
    "publisher": "Elsevier",
    "info": [
      "https://www.journals.elsevier.com/advances-in-engineering-software"
    ],
    "forauthor": "https://www.elsevier.com/journals/advances-in-engineering-software/0965-9978/guide-for-authors",
    "indexing": "INSPEC, Scopus",
    "issn": "0965-9978",
    "mark": "30.0"
  },
  {
    "name": "International Journal Of Web And Grid Services",
    "publisher": "Inderscience Publishers Inderscience Publishers",
    "info": [
      "http://www.inderscience.com/jhome.php?jcode=ijwgs",
      "https://www.researchgate.net/journal/1741-1106_International_Journal_of_Web_and_Grid_Services"
    ],
    "forauthor": "",
    "indexing": "Scopus",
    "issn": "1741-1106",
    "mark": "30.0"
  },
  {
    "name": "Ieee-acm Transactions On Audio Speech And Language Processing",
    "publisher": "IEEE Signal Processing Society",
    "info": [
      "https://dl.acm.org/citation.cfm?id=J1508",
      "https://ieeexplore.ieee.org/xpl/aboutJournal.jsp?punumber=6570655"
    ],
    "forauthor": "",
    "indexing": "Inspec",
    "issn": "2329-9290",
    "mark": "25.0"
  },
  {
    "name": "Parallel Computing",
    "publisher": "Elsevier",
    "info": [
      "https://www.journals.elsevier.com/parallel-computing/"
    ],
    "forauthor": "https://www.elsevier.com/journals/parallel-computing/0167-8191/guide-for-authors",
    "indexing": "INSPEC Information Services, Scopus",
    "issn": "0167-8191",
    "mark": "35.0"
  },
  {
    "name": "Journal Of Logical And Algebraic Methods In Programming",
    "publisher": "Elsevier",
    "info": [
      "https://www.journals.elsevier.com/journal-of-logical-and-algebraic-methods-in-programming"
    ],
    "forauthor": "https://www.elsevier.com/journals/journal-of-logical-and-algebraic-methods-in-programming/2352-2208/guide-for-authors",
    "indexing": "Scopus, Inspec",
    "issn": "2352-2208",
    "mark": "20.0"
  },
  {
    "name": "Acm Transactions On Storage",
    "publisher": "ACM New York",
    "info": [
      "https://dl.acm.org/citation.cfm?id=J960",
      "https://dl.acm.org/citation.cfm?id=3208078&picked=prox"
    ],
    "forauthor": "",
    "indexing": "Scopus",
    "issn": "1553-3077",
    "mark": "25.0"
  },
  {
    "name": "Quantum Electronics",
    "publisher": "Institute of Physics and Turpion",
    "info": [
      "https://elibrary.ru/title_about.asp?id=9442",
      "https://en.wikipedia.org/wiki/Quantum_Electronics_(journal)"
    ],
    "forauthor": "",
    "indexing": "Scopus, Inspec",
    "issn": "1063-7818",
    "mark": "20.0"
  },
  {
    "name": "Ieee Circuits And Systems Magazine",
    "publisher": "IEEE Circuits and Systems Society",
    "info": [
      "https://ieeexplore.ieee.org/xpl/aboutJournal.jsp?punumber=7384"
    ],
    "forauthor": "",
    "indexing": "Scopus",
    "issn": "1531-636X",
    "mark": "40.0"
  },
  {
    "name": "Ieee Transactions On Circuits And Systems Ii-express Briefs",
    "publisher": "IEEE Circuits and Systems Society",
    "info": [
      "https://ieeexplore.ieee.org/xpl/aboutJournal.jsp?punumber=8920"
    ],
    "forauthor": "",
    "indexing": "Scopus",
    "issn": "1549-7747",
    "mark": "25.0"
  },
  {
    "name": "Cluster Computing-the Journal Of Networks Software Tools And Applications",
    "publisher": "Springer",
    "info": [
      "https://link.springer.com/journal/10586",
      "https://link.springer.com/journal/volumesAndIssues/10586",
      "https://www.springer.com/computer/communication+networks/journal/10586"
    ],
    "forauthor": "https://www.springer.com/computer/communication+networks/journal/10586",
    "indexing": "SCOPUS",
    "issn": "1386-7857",
    "mark": "30.0"
  },
  {
    "name": "European Journal Of Information Systems",
    "publisher": "Springer",
    "info": [
      "https://link.springer.com/journal/41303",
      "https://link.springer.com/journal/volumesAndIssues/41303",
      "https://www.springer.com/computer/database+management+%26+information+retrieval/journal/10844"
    ],
    "forauthor": "https://www.springer.com/computer/database+management+%26+information+retrieval/journal/10844",
    "indexing": "SCOPUS",
    "issn": "0960-085X",
    "mark": "40.0"
  },
  {
    "name": "Software Testing Verification & Reliability",
    "publisher": "John Wiley and Sons Ltd. Chichester",
    "info": [
      "https://dl.acm.org/citation.cfm?id=2389469",
      "https://onlinelibrary.wiley.com/journal/10991689"
    ],
    "forauthor": "https://www.wiley.com/WileyCDA/Section/id-810813.html",
    "indexing": "Scopus",
    "issn": "0960-0833",
    "mark": "30.0"
  },
  {
    "name": "Ad Hoc Networks",
    "publisher": "Elsevier",
    "info": [
      "https://www.journals.elsevier.com/ad-hoc-networks/"
    ],
    "forauthor": "https://www.elsevier.com/journals/ad-hoc-networks/1570-8705/guide-for-authors",
    "indexing": "INSPEC",
    "issn": "1570-8705",
    "mark": "35.0"
  },
  {
    "name": "Acm Transactions On Programming Languages And Systems",
    "publisher": "ACM New York",
    "info": [
      "https://dl.acm.org/citation.cfm?id=J783",
      "https://dl.acm.org/citation.cfm?id=3229520&picked=prox"
    ],
    "forauthor": "",
    "indexing": "Scopus",
    "issn": "0164-0925",
    "mark": "30.0"
  },
  {
    "name": "Journal Of Circuits Systems And Computers",
    "publisher": "World Scientific (Singapore)",
    "info": [
      "https://www.worldscientific.com/worldscinet/jcsc",
      "http://www.guide2research.com/journal/journal-of-circuits-systems-and-computers"
    ],
    "forauthor": "",
    "indexing": "Scopus",
    "issn": "0218-1266",
    "mark": "15.0"
  },
  {
    "name": "Iet Image Processing",
    "publisher": "Publisher",
    "info": [
      "http://digital-library.theiet.org/content/journals/iet-ipr",
      "http://digital-library.theiet.org/content/journals/iet-ipr/info/about",
      "http://digital-library.theiet.org/content/journals/iet-ipr/12/6"
    ],
    "forauthor": "",
    "indexing": "indexing",
    "issn": "1751-9659",
    "mark": "20.0"
  },
  {
    "name": "Acm Transactions On Internet Technology",
    "publisher": "ACM New York",
    "info": [
      "https://dl.acm.org/citation.cfm?id=J780",
      "https://dl.acm.org/citation.cfm?id=3185332&picked=prox"
    ],
    "forauthor": "https://toit.acm.org/authors.cfm",
    "indexing": "indexing",
    "issn": "1533-5399",
    "mark": "25.0"
  },
  {
    "name": "Journal Of Logic And Algebraic Programming",
    "publisher": "Elsevier",
    "info": [
      "https://www.journals.elsevier.com/the-journal-of-logic-and-algebraic-programming"
    ],
    "forauthor": "",
    "indexing": "Scopus",
    "issn": "1567-8326",
    "mark": "35.0"
  },
  {
    "name": "Acm Transactions On Computer Systems",
    "publisher": "ACM New York",
    "info": [
      "https://dl.acm.org/citation.cfm?id=J774",
      "https://tocs.acm.org/"
    ],
    "forauthor": "",
    "indexing": "INspec",
    "issn": "0734-2071",
    "mark": "40.0"
  },
  {
    "name": "Canadian Journal Of Electrical And Computer Engineering-revue Canadienne De Genie Electrique Et Informatique",
    "publisher": "Publisher",
    "info": [
      "http://journal.ieee.ca/",
      "http://journal.ieee.ca/aboutcjece.html"
    ],
    "forauthor": "",
    "indexing": "indexing",
    "issn": "0840-8688",
    "mark": ""
  },
  {
    "name": "Advances In Computers",
    "publisher": "Publisher",
    "info": [
      "https://www.sciencedirect.com/bookseries/advances-in-computers",
      "https://www.sciencedirect.com/bookseries/advances-in-computers/vol/106/suppl/C"
    ],
    "forauthor": "",
    "indexing": "Inspec",
    "issn": "0065-2458",
    "mark": "15.0"
  },
  {
    "name": "Ieee Computer Architecture Letters",
    "publisher": "IEEE Computer Society",
    "info": [
      "https://ieeexplore.ieee.org/xpl/aboutJournal.jsp?punumber=10208",
      "https://dl.acm.org/citation.cfm?id=1591872"
    ],
    "forauthor": "",
    "indexing": "Scopus",
    "issn": "1556-6056",
    "mark": "25.0"
  },
  {
    "name": "Acm Transactions On Autonomous And Adaptive Systems",
    "publisher": "ACM New York",
    "info": [
      "https://dl.acm.org/citation.cfm?id=J1010",
      "https://taas.acm.org/"
    ],
    "forauthor": "https://taas.acm.org/authors.cfm",
    "indexing": "Scopus",
    "issn": "1556-4665",
    "mark": "25.0"
  },
  {
    "name": "Acm Transactions On Modeling And Computer Simulation",
    "publisher": "ACM New York",
    "info": [
      "https://dl.acm.org/citation.cfm?id=J781"
    ],
    "forauthor": "",
    "indexing": "scopus",
    "issn": "1049-3301",
    "mark": "25.0"
  },
  {
    "name": "Iet Information Security",
    "publisher": "Publisher",
    "info": [
      "http://digital-library.theiet.org/content/journals/iet-ifs",
      "http://digital-library.theiet.org/content/journals/iet-ifs/info/about"
    ],
    "forauthor": "http://digital-library.theiet.org/journals/author-guide",
    "indexing": "Scopus",
    "issn": "1751-8709",
    "mark": "25.0"
  },
  {
    "name": "Science China-technological Sciences",
    "publisher": "Springer",
    "info": [
      "https://link.springer.com/journal/11431",
      "https://link.springer.com/journal/volumesAndIssues/11431",
      "https://www.springer.com/engineering/journal/11431"
    ],
    "forauthor": "https://www.springer.com/engineering/journal/11431",
    "indexing": "SCOPUS",
    "issn": "1674-7321",
    "mark": "30.0"
  },
  {
    "name": "Acm Transactions On Information And System Security",
    "publisher": "ACM New York",
    "info": [
      "https://dl.acm.org/citation.cfm?id=J789",
      "https://dl.acm.org/citation.cfm?id=2928292&picked=prox"
    ],
    "forauthor": "",
    "indexing": "Inspec",
    "issn": "1094-9224",
    "mark": "30.0"
  },
  {
    "name": "Ieee Transactions On Mobile Computing",
    "publisher": "IEEE Computer Society, IEEE Circuits and Systems Society, IEEE Communications Society",
    "info": [
      "https://ieeexplore.ieee.org/xpl/aboutJournal.jsp?punumber=7755"
    ],
    "forauthor": "",
    "indexing": "indexing",
    "issn": "1536-1233",
    "mark": "45.0"
  },
  {
    "name": "Annals Of Science",
    "publisher": "Taylor & Francis",
    "info": [
      "https://en.wikipedia.org/wiki/Annals_of_Science",
      "https://www.tandfonline.com/loi/tasc20",
      "https://www.tandfonline.com/action/journalInformation?show=aimsScope&journalCode=tasc20"
    ],
    "forauthor": "https://www.tandfonline.com/action/authorSubmission?show=instructions&journalCode=tasc20",
    "indexing": "indexing",
    "issn": "0003-3790",
    "mark": "25.0"
  },
  {
    "name": "Iet Computer Vision",
    "publisher": "Institution of Engineering and Technology",
    "info": [
      "http://digital-library.theiet.org/content/journals/iet-cvi",
      "http://digital-library.theiet.org/content/journals/iet-cvi/info/about",
      "https://ieeexplore.ieee.org/xpl/aboutJournal.jsp?punumber=4159597"
    ],
    "forauthor": "",
    "indexing": "Scopus",
    "issn": "1751-9632",
    "mark": "20.0"
  },
  {
    "name": "Acm Transactions On Applied Perception",
    "publisher": "ACM New York",
    "info": [
      "https://dl.acm.org/citation.cfm?id=J932",
      "https://dl.acm.org/citation.cfm?id=3190502&picked=prox",
      "https://en.wikipedia.org/wiki/ACM_Transactions_on_Applied_Perception"
    ],
    "forauthor": "",
    "indexing": "Inspec",
    "issn": "1544-3558",
    "mark": "35.0"
  },
  {
    "name": "Acm Transactions On Multimedia Computing Communications And Applications",
    "publisher": "ACM New York",
    "info": [
      "https://dl.acm.org/citation.cfm?id=J961",
      "http://l2u.su/qGw"
    ],
    "forauthor": "",
    "indexing": "Scopus",
    "issn": "1551-6857",
    "mark": "30.0"
  },
  {
    "name": "Theoretical Computer Science",
    "publisher": "Elsevier",
    "info": [
      "https://www.journals.elsevier.com/theoretical-computer-science/"
    ],
    "forauthor": "https://www.elsevier.com/journals/theoretical-computer-science/0304-3975/guide-for-authors",
    "indexing": "Scopus, INSPEC Information Services",
    "issn": "0304-3975",
    "mark": "20.0"
  },
  {
    "name": "Ieee Transactions On Multimedia",
    "publisher": "Institute of Electrical and Electronics Engineers",
    "info": [
      "https://ieeexplore.ieee.org/xpl/aboutJournal.jsp?punumber=6046",
      "https://en.wikipedia.org/wiki/IEEE_Transactions_on_Multimedia"
    ],
    "forauthor": "",
    "indexing": "Inspec",
    "issn": "1520-9210",
    "mark": "40.0"
  },
  {
    "name": "International Journal Of Applied Mathematics And Computer Science",
    "publisher": "DE GRUYTER OPEN",
    "info": [
      "https://content.sciendo.com/view/journals/amcs/amcs-overview.xml"
    ],
    "forauthor": "https://www.amcs.uz.zgora.pl/?action=guide",
    "indexing": "Elsevier - SCOPUS,Inspec, Clarivate Analytics - Web of Science, Index Copernicus",
    "issn": "1641-876X",
    "mark": "25.0"
  },
  {
    "name": "Analysis & Pde",
    "publisher": "Publisher",
    "info": [
      "https://msp.org/apde/about/journal/about.html",
      "https://msp.org/apde/2018/11-6/index.xhtml"
    ],
    "forauthor": "https://www.amcs.uz.zgora.pl/?action=online",
    "indexing": "indexing",
    "issn": "1948-206X",
    "mark": "40.0"
  },
  {
    "name": "Acm Transactions On Database Systems",
    "publisher": "ACM New York",
    "info": [
      "https://dl.acm.org/citation.cfm?id=J777",
      "https://tods.acm.org/"
    ],
    "forauthor": "https://tods.acm.org/authors.cfm",
    "indexing": "Scopus",
    "issn": "0362-5915",
    "mark": "30.0"
  },
  {
    "name": "International Journal On Artificial Intelligence Tools",
    "publisher": "World scientific",
    "info": [
      "https://www.worldscientific.com/worldscinet/ijait",
      "https://www.worldscientific.com/page/ijait/aims-scope"
    ],
    "forauthor": "https://www.worldscientific.com/page/ijait/submission-guidelines",
    "indexing": "Scopus",
    "issn": "0218-2130",
    "mark": "15.0"
  },
  {
    "name": "International Journal Of Foundations Of Computer Science",
    "publisher": "World scientific",
    "info": [
      "https://www.worldscientific.com/worldscinet/ijfcs",
      "https://www.worldscientific.com/page/ijfcs/aims-scope",
      "https://www.worldscientific.com/toc/ijfcs/28/01"
    ],
    "forauthor": "https://www.worldscientific.com/page/ijfcs/submission-guidelines",
    "indexing": "Scopus",
    "issn": "0129-0541",
    "mark": "15.0"
  },
  {
    "name": "Advances In Space Research",
    "publisher": "Elsevier",
    "info": [
      "Info"
    ],
    "forauthor": "https://www.elsevier.com/journals/advances-in-space-research/0273-1177/guide-for-authors",
    "indexing": "INSPEC, Scopus, Web of Science",
    "issn": "0273-1177",
    "mark": "20.0"
  },
  {
    "name": "Ieee Transactions On Nanotechnology",
    "publisher": "IEEE Nanotechnology Council",
    "info": [
      "https://ieeexplore.ieee.org/xpl/aboutJournal.jsp?punumber=7729",
      "https://www.scimagojr.com/journalsearch.php?q=15464&tip=sid"
    ],
    "forauthor": "",
    "indexing": "Scopus",
    "issn": "1536-125X",
    "mark": "30.0"
  },
  {
    "name": "Ieee Internet Computing",
    "publisher": "IEEE Computer Society",
    "info": [
      "https://ieeexplore.ieee.org/xpl/aboutJournal.jsp?punumber=4236",
      "https://dl.acm.org/citation.cfm?id=642462"
    ],
    "forauthor": "",
    "indexing": "Scopus",
    "issn": "1089-7801",
    "mark": "45.0"
  },
  {
    "name": "Applicable Analysis And Discrete Mathematics",
    "publisher": "University of Belgrade - School of Electrical Engineering",
    "info": [
      "http://pefmath.etf.rs/",
      "http://pefmath.etf.rs/component/papers/?vol=12&no=1&year=2018",
      "http://road.issn.org/issn/2406-100X-applicable-analysis-and-discrete-mathematics#.WxvbVUiFNPY"
    ],
    "forauthor": "http://pefmath.etf.rs/instructions-for-authors.html",
    "indexing": "Web of Science",
    "issn": "1452-8630",
    "mark": "35.0"
  },
  {
    "name": "Iet Computers And Digital Techniques",
    "publisher": "Institution of Engineering and Technology",
    "info": [
      "http://digital-library.theiet.org/content/journals/iet-cdt",
      "http://digital-library.theiet.org/content/journals/iet-cdt/info/about",
      "https://ieeexplore.ieee.org/xpl/aboutJournal.jsp?punumber=4117424"
    ],
    "forauthor": "",
    "indexing": "Inpsec",
    "issn": "1751-8601",
    "mark": "15.0"
  },
  {
    "name": "Ieee Transactions On Very Large Scale Integration (vlsi) Systems",
    "publisher": "IEEE Educational Activities Department Piscataway",
    "info": [
      "https://ieeexplore.ieee.org/xpl/aboutJournal.jsp?punumber=92",
      "https://dl.acm.org/citation.cfm?id=1825675"
    ],
    "forauthor": "",
    "indexing": "Scopus",
    "issn": "1063-8210",
    "mark": "30.0"
  },
  {
    "name": "Mobile Networks & Applications",
    "publisher": "Springer",
    "info": [
      "https://link.springer.com/journal/11036",
      "https://link.springer.com/journal/volumesAndIssues/11036",
      "https://www.springer.com/engineering/signals/journal/11036"
    ],
    "forauthor": "https://www.springer.com/engineering/signals/journal/11036",
    "indexing": "SCOPUS",
    "issn": "1383-469X",
    "mark": "30.0"
  },
  {
    "name": "Automatika",
    "publisher": "Publisher",
    "info": [
      "https://automatika.korema.hr/index.php/automatika",
      "http://road.issn.org/issn/1848-3380-automatika#.WxvdL0iFNPY"
    ],
    "forauthor": "https://automatika.korema.hr/index.php/automatika/information/authors",
    "indexing": "SCOPUS, INSPEC (Institution of Electrical Engineers)",
    "issn": "0005-1144",
    "mark": "15.0"
  },
  {
    "name": "Acm Transactions On Embedded Computing Systems",
    "publisher": "ACM New York",
    "info": [
      "https://dl.acm.org/citation.cfm?id=J840",
      "https://www.researchgate.net/journal/1539-9087_ACM_Transactions_on_Embedded_Computing_Systems"
    ],
    "forauthor": "",
    "indexing": "Scopus",
    "issn": "1539-9087",
    "mark": "30.0"
  },
  {
    "name": "Acm Transactions On Sensor Networks",
    "publisher": "ACM New York,",
    "info": [
      "https://dl.acm.org/citation.cfm?id=J981",
      "https://tosn.acm.org/"
    ],
    "forauthor": "https://tosn.acm.org/authors.cfm",
    "indexing": "Scopus",
    "issn": "1550-4859",
    "mark": "40.0"
  },
  {
    "name": "Ieee Systems Journal",
    "publisher": "IEEE Systems Council",
    "info": [
      "https://ieeexplore.ieee.org/xpl/RecentIssue.jsp?punumber=4267003&year=2009"
    ],
    "forauthor": "",
    "indexing": "Scopus",
    "issn": "1932-8184",
    "mark": "35.0"
  },
  {
    "name": "Journal Of Systems Architecture",
    "publisher": "Elsevier",
    "info": [
      "https://www.journals.elsevier.com/journal-of-systems-architecture/"
    ],
    "forauthor": "https://www.elsevier.com/journals/journal-of-systems-architecture/1383-7621/guide-for-authors",
    "indexing": "Scopus, INSPEC Information Services",
    "issn": "1383-7621",
    "mark": "20.0"
  },
  {
    "name": "Ieee Journal Of Selected Topics In Signal Processing",
    "publisher": "IEEE Signal Processing Society",
    "info": [
      "https://ieeexplore.ieee.org/xpl/aboutJournal.jsp?punumber=4200690"
    ],
    "forauthor": "",
    "indexing": "Inspec",
    "issn": "1932-4553",
    "mark": "45.0"
  },
  {
    "name": "Journal Of The Association For Information Science And Technology",
    "publisher": "John Wiley & Sons",
    "info": [
      "https://www.wiley.com/en-us/Journal+of+the+Association+for+Information+Science+and+Technology-p-9780471541394",
      "https://onlinelibrary.wiley.com/journal/15322890",
      "http://miar.ub.edu/issn/2330-1643"
    ],
    "forauthor": "",
    "indexing": "Scopus, INSPEC",
    "issn": "2330-1635",
    "mark": "30.0"
  },
  {
    "name": "Asian Journal Of Control",
    "publisher": "John Wiley & Sons",
    "info": [
      "https://www.wiley.com/en-us/Asian+Journal+of+Control-p-9780JRNL63603",
      "https://dl.acm.org/citation.cfm?id=J1587",
      "https://dl.acm.org/citation.cfm?id=3080011&picked=prox"
    ],
    "forauthor": "",
    "indexing": "Scopus",
    "issn": "1561-8625",
    "mark": "25.0"
  },
  {
    "name": "Advances In Materials Science And Engineering",
    "publisher": "Hindawi Publishing Corporation",
    "info": [
      "https://www.hindawi.com/journals/amse/biblio/",
      "https://www.hindawi.com/journals/amse/"
    ],
    "forauthor": "",
    "indexing": "INSPEC, Scopus",
    "issn": "1687-8434",
    "mark": "20.0"
  },
  {
    "name": "Ieice Transactions On Fundamentals Of Electronics Communications And Computer Sciences",
    "publisher": "Oxford University Press Oxford",
    "info": [
      "https://www.jstage.jst.go.jp/browse/transfun",
      "https://www.jstage.jst.go.jp/browse/transfun/list/-char/en"
    ],
    "forauthor": "https://www.jstage.jst.go.jp/static/pages/ForAuthors/-char/en",
    "indexing": "Scopus",
    "issn": "0916-8508",
    "mark": ""
  },
  {
    "name": "International Journal Of Wavelets Multiresolution And Information Processing",
    "publisher": "World scientific",
    "info": [
      "https://www.worldscientific.com/worldscinet/ijwmip",
      "https://www.worldscientific.com/page/ijwmip/aims-scope"
    ],
    "forauthor": "https://www.worldscientific.com/page/ijwmip/submission-guidelines",
    "indexing": "Scopus, INSPEC",
    "issn": "0219-6913",
    "mark": "15.0"
  },
  {
    "name": "International Journal Of Computer Mathematics",
    "publisher": "Taylor & Francis",
    "info": [
      "https://www.tandfonline.com/loi/gcom20",
      "https://www.tandfonline.com/action/journalInformation?show=aimsScope&journalCode=gcom20"
    ],
    "forauthor": "https://www.tandfonline.com/action/authorSubmission?show=instructions&journalCode=gcom20",
    "indexing": "Scopus",
    "issn": "0020-7160",
    "mark": "20.0"
  },
  {
    "name": "Applied Numerical Mathematics",
    "publisher": "Elsevier",
    "info": [
      "https://www.journals.elsevier.com/applied-numerical-mathematics"
    ],
    "forauthor": "https://www.elsevier.com/journals/applied-numerical-mathematics/0168-9274/guide-for-authors",
    "indexing": "Scopus, Web of Science",
    "issn": "0168-9274",
    "mark": "35.0"
  },
  {
    "name": "Computer Standards & Interfaces",
    "publisher": "Elsevier",
    "info": [
      "https://www.journals.elsevier.com/computer-standards-and-interfaces"
    ],
    "forauthor": "https://www.elsevier.com/journals/computer-standards-and-interfaces/0920-5489/guide-for-authors",
    "indexing": "Scopus, INSPEC Information Services,",
    "issn": "0920-5489",
    "mark": "30.0"
  },
  {
    "name": "Ieee Transactions On Computer-aided Design Of Integrated Circuits And Systems",
    "publisher": "Institute of Electrical and Electronics Engineers",
    "info": [
      "https://en.wikipedia.org/wiki/IEEE_Transactions_on_Computer-Aided_Design_of_Integrated_Circuits_and_Systems",
      "https://ieeexplore.ieee.org/xpl/aboutJournal.jsp?punumber=43"
    ],
    "forauthor": "",
    "indexing": "Scopus",
    "issn": "0278-0070",
    "mark": "25.0"
  },
  {
    "name": "Journal Of Supercomputing",
    "publisher": "Springer",
    "info": [
      "https://link.springer.com/journal/11227",
      "https://link.springer.com/journal/volumesAndIssues/11227",
      "https://www.springer.com/computer/swe/journal/11227"
    ],
    "forauthor": "https://www.springer.com/computer/swe/journal/11227",
    "indexing": "SCOPUS",
    "issn": "0920-8542",
    "mark": "20.0"
  },
  {
    "name": "Acm Transactions On Intelligent Systems And Technology",
    "publisher": "ACM New York",
    "info": [
      "https://dl.acm.org/citation.cfm?id=J1318",
      "https://dl.acm.org/citation.cfm?id=3210369&picked=prox",
      "https://tist.acm.org/"
    ],
    "forauthor": "https://tist.acm.org/authors.cfm",
    "indexing": "Scopus",
    "issn": "2157-6904",
    "mark": "50.0"
  },
  {
    "name": "Ieee Signal Processing Letters",
    "publisher": "IEEE Signal Processing Society",
    "info": [
      "https://ieeexplore.ieee.org/xpl/aboutJournal.jsp?punumber=97"
    ],
    "forauthor": "",
    "indexing": "indexing",
    "issn": "1070-9908",
    "mark": "30.0"
  },
  {
    "name": "Journal Of The Association For Information Systems",
    "publisher": "Publisher",
    "info": [
      "http://aisel.aisnet.org/jais/",
      "http://aisel.aisnet.org/jais/about.html"
    ],
    "forauthor": "http://aisel.aisnet.org/jais/authorinfo.html",
    "indexing": "Scopus",
    "issn": "1536-9323",
    "mark": "40.0"
  },
  {
    "name": "Logical Methods In Computer Science",
    "publisher": "Technical University of Braunschweig",
    "info": [
      "http://road.issn.org/issn/1860-5974-logical-methods-in-computer-science-#.WxvjpkiFNPY"
    ],
    "forauthor": "",
    "indexing": "Scopus",
    "issn": "1860-5974",
    "mark": "25.0"
  },
  {
    "name": "Bell Labs Technical Journal",
    "publisher": "IEEE (Nokia Bell Labs)",
    "info": [
      "https://en.wikipedia.org/wiki/Bell_Labs_Technical_Journal",
      "https://ieeexplore.ieee.org/xpl/aboutJournal.jsp?punumber=6731002"
    ],
    "forauthor": "",
    "indexing": "Scopus",
    "issn": "1089-7089",
    "mark": "20.0"
  },
  {
    "name": "Advances In Electrical And Computer Engineering",
    "publisher": "Stefan cel Mare University of Suceava",
    "info": [
      "http://www.aece.ro/"
    ],
    "forauthor": "http://www.aece.ro/authors.php",
    "indexing": "SCOPUS, INSPEC",
    "issn": "1582-7445",
    "mark": "15.0"
  },
  {
    "name": "Ieee Transactions On Industrial Electronics",
    "publisher": "IEEE Industrial Electronics Society",
    "info": [
      "https://ieeexplore.ieee.org/xpl/aboutJournal.jsp?punumber=41"
    ],
    "forauthor": "http://open.ieee.org/index.php/for-authors/author-benefits/",
    "indexing": "Scopus",
    "issn": "0278-0046",
    "mark": "50.0"
  },
  {
    "name": "International Journal Of Information Technology & Decision Making",
    "publisher": "World Scientific",
    "info": [
      "https://www.worldscientific.com/worldscinet/ijitdm",
      "https://www.worldscientific.com/page/ijitdm/aims-scope"
    ],
    "forauthor": "https://www.worldscientific.com/page/ijitdm/submission-guidelines",
    "indexing": "Scopus, INSPEC",
    "issn": "0219-6220",
    "mark": "30.0"
  },
  {
    "name": "Ieee Journal Of Selected Topics In Quantum Electronics",
    "publisher": "IEEE Photonics Society",
    "info": [
      "https://ieeexplore.ieee.org/xpl/aboutJournal.jsp?punumber=2944",
      "https://en.wikipedia.org/wiki/IEEE_Journal_of_Selected_Topics_in_Quantum_Electronics"
    ],
    "forauthor": "",
    "indexing": "indexing",
    "issn": "1077-260X",
    "mark": "45.0"
  },
  {
    "name": "Computer Communications",
    "publisher": "Elsevier",
    "info": [
      "https://www.journals.elsevier.com/computer-communications/"
    ],
    "forauthor": "https://www.elsevier.com/journals/computer-communications/0140-3664/guide-for-authors",
    "indexing": "Scopus, INSPEC",
    "issn": "0140-3664",
    "mark": "30.0"
  },
  {
    "name": "Neural Computing & Applications",
    "publisher": "Springer",
    "info": [
      "https://link.springer.com/journal/521",
      "https://link.springer.com/journal/volumesAndIssues/521",
      "https://www.springer.com/computer/ai/journal/521"
    ],
    "forauthor": "https://www.springer.com/computer/ai/journal/521",
    "indexing": "Scopus",
    "issn": "0941-0643",
    "mark": "25.0"
  },
  {
    "name": "Acm Journal On Emerging Technologies In Computing Systems",
    "publisher": "ACM New York",
    "info": [
      "https://dl.acm.org/citation.cfm?id=J967",
      "https://dl.acm.org/citation.cfm?id=3227199&picked=prox",
      "https://jetc.acm.org/"
    ],
    "forauthor": "https://jetc.acm.org/authors.cfm",
    "indexing": "Scopus",
    "issn": "1550-4832",
    "mark": "20.0"
  },
  {
    "name": "Ieee Control Systems Magazine",
    "publisher": "IEEE Control Systems Society",
    "info": [
      "https://ieeexplore.ieee.org/xpl/aboutJournal.jsp?punumber=37"
    ],
    "forauthor": "",
    "indexing": "Scopus",
    "issn": "1066-033X",
    "mark": "50.0"
  },
  {
    "name": "Ieee Transactions On Cybernetics",
    "publisher": "IEEE Systems, Man, and Cybernetics Society",
    "info": [
      "https://ieeexplore.ieee.org/xpl/aboutJournal.jsp?punumber=6221036"
    ],
    "forauthor": "",
    "indexing": "Scopus",
    "issn": "2168-2267",
    "mark": "50.0"
  },
  {
    "name": "Aeu-international Journal Of Electronics And Communications",
    "publisher": "Elsevier",
    "info": [
      "https://www.journals.elsevier.com/aeu-international-journal-of-electronics-and-communications"
    ],
    "forauthor": "https://www.elsevier.com/journals/aeu-international-journal-of-electronics-and-communications/1434-8411/guide-for-authors",
    "indexing": "Scopus, INSPEC",
    "issn": "1434-8411",
    "mark": "20.0"
  },
  {
    "name": "Ieee Transactions On Circuits And Systems I-regular Papers",
    "publisher": "IEEE Circuits and Systems Society",
    "info": [
      "https://ieeexplore.ieee.org/xpl/aboutJournal.jsp?punumber=8919"
    ],
    "forauthor": "",
    "indexing": "Inspec",
    "issn": "1549-8328",
    "mark": "35.0"
  },
  {
    "name": "Acm Transactions On The Web",
    "publisher": "ACM New York",
    "info": [
      "https://dl.acm.org/citation.cfm?id=J1062",
      "https://dl.acm.org/citation.cfm?id=3176641&picked=prox",
      "https://tweb.acm.org/"
    ],
    "forauthor": "https://tweb.acm.org/authors.cfm",
    "indexing": "Scopus",
    "issn": "1559-1131",
    "mark": "40.0"
  },
  {
    "name": "Advances In Production Engineering & Management",
    "publisher": "Production Engineering Institute (PEI), University of Maribor, Faculty of Mechanical Engineering",
    "info": [
      "http://apem-journal.org/Archives.html",
      "https://en.wikipedia.org/wiki/Advances_in_Production_Engineering_%26_Management"
    ],
    "forauthor": "http://apem-journal.org/ForAuthors.html",
    "indexing": "Scopus, Inspec, Web of Science",
    "issn": "1854-6250",
    "mark": "20.0"
  },
  {
    "name": "Automatica",
    "publisher": "Elsevier",
    "info": [
      "https://www.journals.elsevier.com/automatica/"
    ],
    "forauthor": "https://www.elsevier.com/journals/automatica/0005-1098/guide-for-authors",
    "indexing": "INSPEC,Scopus, Web of Science",
    "issn": "0005-1098",
    "mark": "45.0"
  },
  {
    "name": "Ieee Software",
    "publisher": "IEEE Computer Society",
    "info": [
      "https://ieeexplore.ieee.org/xpl/aboutJournal.jsp?punumber=52",
      "https://en.wikipedia.org/wiki/IEEE_Software"
    ],
    "forauthor": "",
    "indexing": "Scopus",
    "issn": "0740-7459",
    "mark": "30.0"
  },
  {
    "name": "Acm Transactions On Information Systems",
    "publisher": "ACM New York",
    "info": [
      "https://dl.acm.org/citation.cfm?id=J779",
      "https://dl.acm.org/citation.cfm?id=3211967&picked=prox"
    ],
    "forauthor": "https://tois.acm.org/authors.cfm",
    "indexing": "Scopus",
    "issn": "1046-8188",
    "mark": "30.0"
  },
  {
    "name": "Discrete Mathematics And Theoretical Computer Science",
    "publisher": "Publisher",
    "info": [
      "https://dmtcs.episciences.org/",
      "http://road.issn.org/issn/1365-8050-discrete-mathematics-and-theoretical-computer-science-#.Wxvp1EiFNPY"
    ],
    "forauthor": "",
    "indexing": "indexing",
    "issn": "1462-7264",
    "mark": "20.0"
  },
  {
    "name": "Ieee Transactions On Computational Intelligence And Ai In Games",
    "publisher": "IEEE Computational Intelligence Society",
    "info": [
      "https://ieeexplore.ieee.org/xpl/aboutJournal.jsp?punumber=4804728",
      "https://www.scimagojr.com/journalsearch.php?q=19700177025&tip=sid&exact=no"
    ],
    "forauthor": "",
    "indexing": "indexing",
    "issn": "1943-068X",
    "mark": "30.0"
  },
  {
    "name": "International Arab Journal Of Information Technology",
    "publisher": "Zarqa University",
    "info": [
      "http://www.iajit.org/",
      "http://iajit.org/index.php?option=com_content&task=view&id=66&Itemid=157",
      "http://www.guide2research.com/journal/international-arab-journal-of-information-technology"
    ],
    "forauthor": "http://iajit.org/index.php?option=com_content&task=view&id=69&Itemid=160",
    "indexing": "indexing",
    "issn": "1683-3198",
    "mark": "15.0"
  },
  {
    "name": "Ieee Transactions On Circuits And Systems For Video Technology",
    "publisher": "IEEE Press Piscataway",
    "info": [
      "https://www.ieee.org/membership-catalog/productdetail/showProductDetailPage.html?product=PER153-PRT",
      "https://dl.acm.org/citation.cfm?id=2322478&picked=prox",
      "https://ieeexplore.ieee.org/xpl/aboutJournal.jsp?punumber=76"
    ],
    "forauthor": "",
    "indexing": "Scopus",
    "issn": "1051-8215",
    "mark": "35.0"
  },
  {
    "name": "Journal Of Automation And Information Sciences",
    "publisher": "Begell Houser",
    "info": [
      "http://www.begellhouse.com/ru/journals/automation-and-information-sciences.html"
    ],
    "forauthor": "http://www.begellhouse.com/ru/forauthors/journals/automation-and-information-sciences.html",
    "indexing": "indexing",
    "issn": "1064-2315",
    "mark": "15.0"
  },
  {
    "name": "Ksii Transactions On Internet And Information Systems",
    "publisher": "Korean Society For Internet Information",
    "info": [
      "http://www.itiis.org/",
      "https://www.dbpia.co.kr/Journal/IssueList/PLCT00001232"
    ],
    "forauthor": "",
    "indexing": "SCOPUS",
    "issn": "1976-7277",
    "mark": "20.0"
  },
  {
    "name": "Circuits Systems And Signal Processing",
    "publisher": "Springer",
    "info": [
      "https://link.springer.com/journal/34",
      "https://link.springer.com/journal/volumesAndIssues/34",
      "https://www.springer.com/engineering/electronics/journal/34"
    ],
    "forauthor": "https://www.springer.com/engineering/electronics/journal/34",
    "indexing": "indexing",
    "issn": "0278-081X",
    "mark": "25.0"
  },
  {
    "name": "Acm Computing Surveys",
    "publisher": "ACM New York",
    "info": [
      "https://dl.acm.org/citation.cfm?id=J204",
      "https://dl.acm.org/citation.cfm?id=3186333&picked=prox",
      "https://csur.acm.org/"
    ],
    "forauthor": "https://csur.acm.org/authors.cfm",
    "indexing": "indexing",
    "issn": "0360-0300",
    "mark": "50.0"
  },
  {
    "name": "Ieee Computer Graphics And Applications",
    "publisher": "IEEE Computer Society",
    "info": [
      "https://ieeexplore.ieee.org/xpl/aboutJournal.jsp?punumber=38"
    ],
    "forauthor": "",
    "indexing": "indexing",
    "issn": "0272-1716",
    "mark": "35.0"
  },
  {
    "name": "Computing In Science & Engineering",
    "publisher": "Publisher",
    "info": [
      "https://ieeexplore.ieee.org/xpl/aboutJournal.jsp?punumber=5992",
      "https://publications.computer.org/cise/",
      "https://www.ieee.org/membership-catalog/productdetail/showProductDetailPage.html?product=PER324-ELE"
    ],
    "forauthor": "",
    "indexing": "indexing",
    "issn": "1521-9615",
    "mark": "35.0"
  },
  {
    "name": "Ieee Transactions On Neural Systems And Rehabilitation Engineering",
    "publisher": "IEEE Engineering in Medicine and Biology Society",
    "info": [
      "https://ieeexplore.ieee.org/xpl/aboutJournal.jsp?punumber=7333"
    ],
    "forauthor": "",
    "indexing": "indexing",
    "issn": "1534-4320",
    "mark": "40.0"
  },
  {
    "name": "Acm Transactions On Algorithms",
    "publisher": "ACM New York,",
    "info": [
      "https://dl.acm.org/citation.cfm?id=J982",
      "https://talg.acm.org/"
    ],
    "forauthor": "https://talg.acm.org/authors.cfm",
    "indexing": "indexing",
    "issn": "1549-6325",
    "mark": "25.0"
  },
  {
    "name": "Automation In Construction",
    "publisher": "Elsevier",
    "info": [
      "https://www.journals.elsevier.com/automation-in-construction/"
    ],
    "forauthor": "https://www.elsevier.com/journals/automation-in-construction/0926-5805/guide-for-authors",
    "indexing": "INSPEC, Scopus",
    "issn": "0926-5805",
    "mark": "40.0"
  },
  {
    "name": "Big Data",
    "publisher": "Mary Ann Liebert, Inc. Publishers",
    "info": [
      "https://www.abe.pl/en/journal/2167-6461/",
      "https://www.ncbi.nlm.nih.gov/nlmcatalog?term=2167-6461%5BISSN%5D"
    ],
    "forauthor": "",
    "indexing": "indexing",
    "issn": "2167-6461",
    "mark": "30.0"
  },
  {
    "name": "Scientific Programming",
    "publisher": "Institute of Science",
    "info": [
      "https://www.hindawi.com/journals/sp/biblio/",
      "https://www.hindawi.com/journals/sp/",
      "https://www.hindawi.com/journals/sp/aims/"
    ],
    "forauthor": "",
    "indexing": "INSPEC, Scopus",
    "issn": "1058-9244",
    "mark": "20.0"
  },
  {
    "name": "Frontiers Of Computer Science",
    "publisher": "Springer",
    "info": [
      "https://link.springer.com/journal/11704",
      "https://link.springer.com/journal/volumesAndIssues/11704",
      "https://www.springer.com/computer/journal/11704"
    ],
    "forauthor": "https://www.springer.com/computer/journal/11704",
    "indexing": "Scopus",
    "issn": "2095-2228",
    "mark": "15.0"
  },
  {
    "name": "PROGRAMMING AND COMPUTER SOFTWARE",
    "publisher": "Springer",
    "info": [
      "https://link.springer.com/journal/11086",
      "https://link.springer.com/journal/volumesAndIssues/11086",
      "https://www.springer.com/computer/journal/11086"
    ],
    "forauthor": "https://www.springer.com/computer/journal/11086",
    "indexing": "SCOPUS",
    "issn": "0361-7688",
    "mark": "15.0"
  },
  {
    "name": "Neural Development",
    "publisher": "Springer",
    "info": [
      "https://www.springer.com/biomed/neuroscience/journal/13064",
      "http://neuraldevelopment.biomedcentral.com/",
      "http://neuraldevelopment.biomedcentral.com/"
    ],
    "forauthor": "https://www.springer.com/biomed/neuroscience/journal/13064",
    "indexing": "Scopus",
    "issn": "1749-8104",
    "mark": "35.0"
  },
  {
    "name": "Formal Aspects Of Computing",
    "publisher": "Springer",
    "info": [
      "https://www.springer.com/computer/theoretical+computer+science/journal/165",
      "http://link.springer.com/journal/165/",
      "http://link.springer.com/journal/volumesAndIssues/165"
    ],
    "forauthor": "https://www.springer.com/computer/theoretical+computer+science/journal/165",
    "indexing": "Scopus",
    "issn": "0934-5043",
    "mark": "20.0"
  },
  {
    "name": "International Journal Of Information Security",
    "publisher": "Springer",
    "info": [
      "https://www.springer.com/computer/security+and+cryptology/journal/10207",
      "http://link.springer.com/journal/10207/",
      "http://link.springer.com/journal/volumesAndIssues/10207"
    ],
    "forauthor": "https://www.springer.com/computer/security+and+cryptology/journal/10207",
    "indexing": "Scopus",
    "issn": "1615-5262",
    "mark": "25.0"
  },
  {
    "name": "Journal Of Information Technology",
    "publisher": "Springer",
    "info": [
      "https://www.springer.com/business+&+management/journal/41265",
      "http://link.springer.com/journal/41265/",
      "http://link.springer.com/journal/41265"
    ],
    "forauthor": "https://www.springer.com/business+&+management/journal/41265",
    "indexing": "",
    "issn": "0268-3962",
    "mark": "45.0"
  },
  {
    "name": "Journal Of Network And Systems Management",
    "publisher": "Springer",
    "info": [
      "https://www.springer.com/computer/communication+networks/journal/10922",
      "http://link.springer.com/journal/10922/",
      "http://link.springer.com/journal/volumesAndIssues/10922"
    ],
    "forauthor": "https://www.springer.com/computer/communication+networks/journal/10922",
    "indexing": "Scopus",
    "issn": "1064-7570",
    "mark": "20.0"
  },
  {
    "name": "Journal Of Intelligent Information Systems",
    "publisher": "Springer",
    "info": [
      "https://www.springer.com/computer/database+management+&+information+retrieval/journal/10844",
      "http://link.springer.com/journal/10844/",
      "http://link.springer.com/journal/volumesAndIssues/10844"
    ],
    "forauthor": "https://www.springer.com/computer/database+management+&+information+retrieval/journal/10844",
    "indexing": "Scopus",
    "issn": "0925-9902",
    "mark": "20.0"
  },
  {
    "name": "Business & Information Systems Engineering",
    "publisher": "Springer",
    "info": [
      "https://www.springer.com/business+&+management/business+information+systems/journal/12599",
      "http://link.springer.com/journal/12599/",
      "http://link.springer.com/journal/volumesAndIssues/12599"
    ],
    "forauthor": "https://www.springer.com/business+&+management/business+information+systems/journal/12599",
    "indexing": "",
    "issn": "1867-0202",
    "mark": "35.0"
  },
  {
    "name": "Formal Methods In System Design",
    "publisher": "Springer",
    "info": [
      "https://www.springer.com/engineering/electronics/journal/10703",
      "http://link.springer.com/journal/10703/",
      "http://link.springer.com/journal/volumesAndIssues/10703"
    ],
    "forauthor": "https://www.springer.com/engineering/electronics/journal/10703",
    "indexing": "Scopus",
    "issn": "0925-9856",
    "mark": "25.0"
  },
  {
    "name": "Advances In Data Analysis And Classification",
    "publisher": "Springer",
    "info": [
      "https://www.springer.com/statistics/journal/11634",
      "http://link.springer.com/journal/11634/",
      "http://link.springer.com/journal/volumesAndIssues/11634"
    ],
    "forauthor": "https://www.springer.com/statistics/journal/11634",
    "indexing": "",
    "issn": "1862-5347",
    "mark": "35.0"
  },
  {
    "name": "International Journal Of Computer Vision",
    "publisher": "Springer",
    "info": [
      "https://www.springer.com/computer/image+processing/journal/11263",
      "http://link.springer.com/journal/11263/",
      "http://link.springer.com/journal/11263"
    ],
    "forauthor": "https://www.springer.com/computer/image+processing/journal/11263",
    "indexing": "",
    "issn": "0920-5691",
    "mark": "45.0"
  },
  {
    "name": "Soft Computing",
    "publisher": "Springer",
    "info": [
      "https://www.springer.com/engineering/computational+intelligence+and+complexity/journal/500",
      "http://link.springer.com/journal/500/",
      "http://link.springer.com/journal/volumesAndIssues/500"
    ],
    "forauthor": "https://www.springer.com/engineering/computational+intelligence+and+complexity/journal/500",
    "indexing": "Scopus",
    "issn": "1432-7643",
    "mark": "25.0"
  },
  {
    "name": "Journal Of Computing In Higher Education",
    "publisher": "Springer",
    "info": [
      "https://www.springer.com/education+&+language/learning+&+instruction/journal/12528",
      "http://link.springer.com/journal/12528/",
      "http://link.springer.com/journal/volumesAndIssues/12528"
    ],
    "forauthor": "https://www.springer.com/education+&+language/learning+&+instruction/journal/12528",
    "indexing": "",
    "issn": "1042-1726",
    "mark": "25.0"
  },
  {
    "name": "Journal Of Computer And Systems Sciences International",
    "publisher": "Springer",
    "info": [
      "https://www.springer.com/engineering/control/journal/11488",
      "http://link.springer.com/journal/volumesAndIssues/11488",
      "http://link.springer.com/journal/volumesAndIssues/11488"
    ],
    "forauthor": "https://www.springer.com/engineering/control/journal/11488",
    "indexing": "Scopus",
    "issn": "1064-2307",
    "mark": "15.0"
  },
  {
    "name": "Automated Software Engineering",
    "publisher": "Springer",
    "info": [
      "https://www.springer.com/computer/ai/journal/10515",
      "http://link.springer.com/journal/10515/",
      "http://link.springer.com/journal/volumesAndIssues/10515"
    ],
    "forauthor": "https://www.springer.com/computer/ai/journal/10515",
    "indexing": "",
    "issn": "0928-8910",
    "mark": "30.0"
  },
  {
    "name": "Advances In Computational Mathematics",
    "publisher": "Springer",
    "info": [
      "https://www.springer.com/mathematics/computational+science+&+engineering/journal/10444",
      "http://link.springer.com/journal/10444/",
      "http://link.springer.com/journal/volumesAndIssues/10444"
    ],
    "forauthor": "https://www.springer.com/mathematics/computational+science+&+engineering/journal/10444",
    "indexing": "Scopus",
    "issn": "1019-7168",
    "mark": "35.0"
  },
  {
    "name": "International Journal Of Parallel Programming",
    "publisher": "Springer",
    "info": [
      "https://www.springer.com/computer/theoretical+computer+science/journal/10766",
      "http://link.springer.com/journal/10766/",
      "http://link.springer.com/journal/volumesAndIssues/10766"
    ],
    "forauthor": "https://www.springer.com/computer/theoretical+computer+science/journal/10766",
    "indexing": "Scopus",
    "issn": "0885-7458",
    "mark": "15.0"
  },
  {
    "name": "Algorithmica",
    "publisher": "Springer",
    "info": [
      "https://www.springer.com/computer/theoretical+computer+science/journal/453",
      "http://link.springer.com/journal/453/",
      "http://link.springer.com/p45500lt12t8"
    ],
    "forauthor": "https://www.springer.com/computer/theoretical+computer+science/journal/453",
    "indexing": "Scopus",
    "issn": "0178-4617",
    "mark": "25.0"
  },
  {
    "name": "Autonomous Agents And Multi-agent Systems",
    "publisher": "Springer",
    "info": [
      "https://www.springer.com/computer/ai/journal/10458",
      "http://link.springer.com/journal/10458/",
      "http://link.springer.com/journal/volumesAndIssues/10458"
    ],
    "forauthor": "https://www.springer.com/computer/ai/journal/10458",
    "indexing": "Scopus",
    "issn": "1387-2532",
    "mark": "25.0"
  },
  {
    "name": "Distributed Computing",
    "publisher": "Springer",
    "info": [
      "https://www.springer.com/computer/communication+networks/journal/446",
      "http://link.springer.com/journal/446/",
      "http://link.springer.com/journal/volumesAndIssues/446"
    ],
    "forauthor": "https://www.springer.com/computer/communication+networks/journal/446",
    "indexing": "Scopus",
    "issn": "0178-2770",
    "mark": "25.0"
  },
  {
    "name": "Arabian Journal For Science And Engineering",
    "publisher": "Springer",
    "info": [
      "https://www.springer.com/engineering/journal/13369",
      "http://link.springer.com/journal/13369/",
      "http://link.springer.com/journal/volumesAndIssues/13369"
    ],
    "forauthor": "https://www.springer.com/engineering/journal/13369",
    "indexing": "",
    "issn": "2193-567X",
    "mark": "20.0"
  },
  {
    "name": "Theory Of Computing Systems",
    "publisher": "Springer",
    "info": [
      "https://www.springer.com/computer/theoretical+computer+science/journal/224",
      "http://link.springer.com/journal/224/",
      "http://link.springer.com/journal/volumesAndIssues/224"
    ],
    "forauthor": "https://www.springer.com/computer/theoretical+computer+science/journal/224",
    "indexing": "Scopus",
    "issn": "1432-4350",
    "mark": "20.0"
  },
  {
    "name": "Building Simulation",
    "publisher": "Springer",
    "info": [
      "https://www.springer.com/engineering/civil+engineering/journal/12273",
      "http://link.springer.com/journal/12273/",
      "http://link.springer.com/journal/volumesAndIssues/12273"
    ],
    "forauthor": "https://www.springer.com/engineering/civil+engineering/journal/12273",
    "indexing": "Scopus",
    "issn": "1996-3599",
    "mark": "25.0"
  },
  {
    "name": "Autonomous Robots",
    "publisher": "Springer",
    "info": [
      "https://www.springer.com/engineering/control/journal/10514",
      "http://link.springer.com/journal/10514/",
      "http://link.springer.com/journal/volumesAndIssues/10514"
    ],
    "forauthor": "https://www.springer.com/engineering/control/journal/10514",
    "indexing": "Scopus",
    "issn": "0929-5593",
    "mark": "35.0"
  },
  {
    "name": "Software Quality Journal",
    "publisher": "Springer",
    "info": [
      "https://www.springer.com/computer/swe/journal/11219",
      "http://link.springer.com/journal/11219/",
      "http://link.springer.com/journal/volumesAndIssues/11219"
    ],
    "forauthor": "https://www.springer.com/computer/swe/journal/11219",
    "indexing": "Scopus,Inspec",
    "issn": "0963-9314",
    "mark": "20.0"
  },
  {
    "name": "Quantum Information Processing",
    "publisher": "Springer",
    "info": [
      "https://www.springer.com/physics/applied+&+technical+physics/journal/11128",
      "http://link.springer.com/journal/volumesAndIssues/11128",
      "#"
    ],
    "forauthor": "https://www.springer.com/physics/applied+&+technical+physics/journal/11128",
    "indexing": "",
    "issn": "1570-0755",
    "mark": "40.0"
  },
  {
    "name": "Analog Integrated Circuits And Signal Processing",
    "publisher": "Springer",
    "info": [
      "https://www.springer.com/engineering/electronics/journal/10470",
      "http://link.springer.com/journal/10470/",
      "http://link.springer.com/journal/volumesAndIssues/10470"
    ],
    "forauthor": "https://www.springer.com/engineering/electronics/journal/10470",
    "indexing": "Scopus",
    "issn": "0925-1030",
    "mark": "15.0"
  },
  {
    "name": "Automation And Remote Control",
    "publisher": "Springer",
    "info": [
      "https://www.springer.com/mathematics/journal/10513",
      "http://link.springer.com/journal/volumesAndIssues/10513",
      "http://link.springer.com/journal/volumesAndIssues/10513"
    ],
    "forauthor": "https://www.springer.com/mathematics/journal/10513",
    "indexing": "Scopus",
    "issn": "0005-1179",
    "mark": "15.0"
  },
  {
    "name": "Knowledge And Information Systems",
    "publisher": "Springer",
    "info": [
      "https://www.springer.com/computer/information+systems+and+applications/journal/10115",
      "http://link.springer.com/journal/10115/",
      "http://link.springer.com/journal/volumesAndIssues/10115"
    ],
    "forauthor": "https://www.springer.com/computer/information+systems+and+applications/journal/10115",
    "indexing": "Scopus",
    "issn": "0219-1377",
    "mark": "35.0"
  },
  {
    "name": "Acta Informatica",
    "publisher": "Springer",
    "info": [
      "https://www.springer.com/computer/theoretical+computer+science/journal/236",
      "http://link.springer.com/journal/236/",
      "http://link.springer.com/journal/volumesAndIssues/236"
    ],
    "forauthor": "https://www.springer.com/computer/theoretical+computer+science/journal/236",
    "indexing": "Scopus",
    "issn": "0001-5903",
    "mark": "15.0"
  },
  {
    "name": "Archives Of Computational Methods In Engineering",
    "publisher": "Springer",
    "info": [
      "https://www.springer.com/engineering/computational+intelligence+and+complexity/journal/11831",
      "http://link.springer.com/journal/11831/",
      "http://link.springer.com/journal/volumesAndIssues/11831"
    ],
    "forauthor": "https://www.springer.com/engineering/computational+intelligence+and+complexity/journal/11831",
    "indexing": "",
    "issn": "1134-3060",
    "mark": "50.0"
  }
]